Workbook

Sheet Method
A1: Method: indicative rooftop solar sizing, generation, savings, payback and CO2 for 20 Oxford sites
A2: OZ. Prepared 9 October 2026; checked by Zara Pashov, 10 October 2026. Workbook sheets: Method (this sheet), Inputs (every number and its source), Results (one row per site), Calculations (every step, every scenario).
A4: 1. Purpose and status
A5: To give an installer an indicative, desktop-derived estimate of system size, year-1 generation, annual saving, simple payback and CO2 avoided for 20 commercial roofs in Oxford City. These are not quotes. No site visit, meter data, structural check or grid-connection check has been made.
A7: 2. How the 20 sites were chosen (summary)
A8: Buildings were ranked with the OZ scorecard v0.3 (roof footprint area and site gap), the method that won the OZ arena run on 2 October 2026, using OpenStreetMap building outlines for Oxford City (local authority E07000178). Buildings with solar already mapped in OpenStreetMap, and sites with their own rooftop solar record in the Renewable Energy Planning Database, were removed. Zara Pashov checked the top 50 sites and 16 further large roofs on satellite imagery on 7 October 2026 and chose these 20: no panels visible, roof judged usable, occupier identified, a mix of sectors.
A10: 3. Decisions taken (Zara Pashov, 9 October 2026)
A11: a) Roof area: main building only (the one checked on satellite). Four sites have more buildings; these are not included.
A12: b) Sizing: roof-limited, i.e. what the usable roof can physically hold. Results above 1 MWp are flagged as likely limited by site demand or grid capacity.
A13: c) Self-consumption: the same three scenario values for every site (40% / 60% / 80%); no published source gives this by sector.
A14: d) Carbon: UK grid-average factor (DESNZ conversion factors), as businesses use for their own carbon reporting.
A15: e) Costs: published commercial price range for capital cost; official DECC 2015 running costs; DESNZ average business electricity price; business export tariffs from Ofgem's Smart Export Guarantee report.
... A65: Attribution: contains OpenStreetMap data © OpenStreetMap contributors, available under the Open Database Licence. Contains public sector information licensed under the Open Government Licence v3.0.

Sheet Inputs
A1: Inputs: every number the calculation uses, with its source
A2: Blue text = a typed input. Black = a formula. Yellow fill = an assumption or a value still to be confirmed. Change any blue cell and every result in the workbook updates.
A4: Parameter | B4: Symbol | C4: Low | D4: Central | E4: High | F4: Unit | G4: Source (see Method, section 8) | H4: Exact quote from the source, or how the value was derived | I4: Status
A5: Share of roof area covered by panels (module area / roof area) | B5: f | C5: =0.49*0.6 -> 0.294 | D5: 0.4 | E5: =0.66*0.7 -> 0.462 | F5: fraction | G5: Low: Bódis et al. (2019). Central: Kakoulaki et al. (2026). High: Gagnon et al. (2016). | H5: Low: "approximately half (49–64%) of EU roofs appeared to be suitable for PV" and "an additional reduction coefficient (60%) has been applied to estimate the net area"; lower bound 0.49 × 0.60. Central: for non-residential buildings "the PV installations were set at 40% of the total rooftop area"; "Spacing between modules and module racks is taken into account in the 25% or 40% installation fraction". High: "49% suitable for medium buildings and 66% for large buildings" and "For flat roofs, the ratio of module area to roof area was assumed to be 0.7"; 0.66 × 0.70. | I5: VERIFIED (quotes opened 09/10/2026)
A6: Module power density | B6: rho | C6: =ROUND($H$25,-1) -> 230 | D6: =ROUND($H$25,-1) -> 230 | E6: =ROUND($H$25,-1) -> 230 | F6: W per m² of module | G6: Median of three current module datasheets (rows 21-23), rounded to the nearest 10 W/m². | H6: Derived: rated power ÷ module area for each datasheet; midpoint of each product's range; median of the three. | I6: VERIFIED datasheets; median is derived
A7: Specific yield (annual generation per kWp) | B7: Y | C7: 922.3 | D7: 922.3 | E7: 922.3 | F7: kWh per kWp per year | G7: PVGIS v5.2 API, EC Joint Research Centre. Retrieved 02/10/2026 during the OZ arena run. | H7: Settings: lat 51.7514, lon −1.2407 (mean location of the 1,790 Oxford City buildings), peak power 1 kWp, system loss 14% (PVGIS default: "We have given a default value of 14% for the overall losses"), tilt 10°, azimuth 0° (south). Output E_y = 922.3. | I7: TO CONFIRM: re-run in the PVGIS web tool (Method, section 7)
A8: Self-consumption (share of generation used on site) | B8: s | C8: 0.4 | D8: 0.6 | E8: 0.8 | F8: fraction | G8: Assumption chosen by Zara Pashov, 09/10/2026. | H8: No published source gives self-consumption by sector. Systems here are sized to the roof, not to site demand, so very high self-use is less likely. To be tested with installers. | I8: ASSUMPTION
A9: Electricity price avoided by self-consumption | B9: p_imp | C9: 24.51 | D9: 24.51 | E9: 24.51 | F9: p per kWh | G9: DESNZ (2026a) Quarterly Energy Prices, September 2026, p. 8. | H9: "In quarter 2 2026, the average electricity price including CCL was 24.51 pence per kWh". All-business average; prices differ by size band. The quoted text does not state the VAT treatment. | I9: VERIFIED (all-business average)
A10: Export price for electricity not used on site | B10: p_exp | C10: 3 | D10: 4.1 | E10: 4.1 | F10: p per kWh | G10: Ofgem (2025) Smart Export Guarantee Annual Report, Year 5 (Apr 2024 – Mar 2025), Figures 2.1–2.3. | H10: Untied business export tariffs named in the report: EDF Variable Business 3 p/kWh (low); Octopus Business 4.1 p/kWh (central and high). These are 2024-25 offers. | I10: VERIFIED (2024-25 tariffs)
A11: Capital cost (installed) | B11: c | C11: 1100 | D11: =($C$11+$E$11)/2 -> 900 | E11: 700 | F11: £ per kWp | G11: Joju Solar (2026) Commercial rooftop solar (trade source). | H11: "the average cost of a commercial rooftop solar installation in the UK is between £700 and £1,100 per kilowatt peak (kWp), with larger installations typically costing less per kWp". Central = midpoint. Joju attributes the figure to the Solar Trade Association; VAT not stated. No official figure newer than 2015 was found. | I11: VERIFIED wording; trade source
A12: Operation and maintenance cost | B12: o | C12: 11.4 | D12: 9.5 | E12: 7.6 | F12: £ per kW per year (2014 prices) | G12: Parsons Brinckerhoff for DECC (2015) Small-Scale Generation Costs Update, section 2.2.4.8. | H12: Band 250–5,000 kW: low 7.6, central 9.5, high 11.4 £/kW/yr. Opex "should include labour, planned maintenance and lifecycle replacement costs". The pessimistic (Low) scenario uses the high cost. 2014 prices, not inflated. | I12: VERIFIED; dated (2014 prices)
A13: Carbon factor for UK grid electricity | B13: g | C13: 0.13096 | D13: 0.13096 | E13: 0.13096 | F13: kg CO2e per kWh | G13: DESNZ (2026b) 2026 GHG conversion factors methodology report, Table 9, p. 36. | H13: Row "2025", electricity GENERATED, total = 0.13096 kg CO2e/kWh (UK grid average, 2025 data). Transmission and distribution losses (0.01299) are not added. | I13: VERIFIED
A14: Annual degradation of panel output (not applied) | B14: d | C14: 0.005 | D14: 0.005 | E14: 0.005 | F14: per year | G14: Jordan and Kurtz (2013). | H14: "Nearly 2000 degradation rates… showing a median value of 0.5%/year." Not applied: all results are year 1. | I14: VERIFIED; documented only
A15: Flag systems larger than | B15: flag | C15: 1000 | D15: 1000 | E15: 1000 | F15: kWp | G15: Decision by Zara Pashov, 09/10/2026. | H15: Systems are sized to the roof. Above 1 MWp they are flagged as likely limited by site demand or grid capacity. | I15: DECISION
A19: Module datasheets used for the power density (row 6)
A20: Module (datasheet) | B20: Rated power, min (W) | C20: Rated power, max (W) | D20: Length (mm) | E20: Width (mm) | F20: W per m², min | G20: W per m², max | H20: Midpoint W per m² | I20: Source URL
A21: LONGi LR7-54HVH 480-500 M (datasheet dated 08/04/2025, marked draft) | B21: 480 | C21: 500 | D21: 1800 | E21: 1134 | F21: =B21/(D21/1000*E21/1000) -> 235.15579 | G21: =C21/(D21/1000*E21/1000) -> 244.95395 | H21: =(F21+G21)/2 -> 240.05487 | I21: https://static.longi.com/LR_7_54_HVH_480_500_M_BGV_01_20250408_BGV_02_568afe65cb.pdf
A22: Jinko Tiger Neo JKM435-460N-54HL4R-(V) (2024) | B22: 435 | C22: 460 | D22: 1762 | E22: 1134 | F22: =B22/(D22/1000*E22/1000) -> 217.70595 | G22: =C22/(D22/1000*E22/1000) -> 230.21779 | H22: =(F22+G22)/2 -> 223.96187 | I22: https://www.jinkosolar.com/uploads/JKM435-460N-54HL4R-(V)-F8-EN.pdf
A23: Trina Vertex N TSM-NEG19RC.20 (2025) | B23: 610 | C23: 635 | D23: 2382 | E23: 1134 | F23: =B23/(D23/1000*E23/1000) -> 225.82656 | G23: =C23/(D23/1000*E23/1000) -> 235.08175 | H23: =(F23+G23)/2 -> 230.45416 | I23: https://static.trinasolar.com/sites/default/files/DT-M-0045_Datasheet_Vertex_NEG19RC.20_EN_2025_B.pdf
G25: Median of midpoints | H25: =MEDIAN(H21:H23) -> 230.45416

Sheet Results
A1: Oxford City: indicative rooftop solar sizing, generation, savings, payback and CO2 for 20 checked sites
A2: Checked by Zara Pashov, 10 October 2026. Indicative desktop estimates from public data, not quotes. Low / Central / High are bundled scenarios (see Method). Figures are for year 1. Inputs and sources: Inputs sheet.
A4: Rank (check sheet) | B4: Site | C4: Found in tab | D4: OSM building type | E4: Buildings on site | F4: OSM footprint, main building (m²) | G4: Roof area used (m²) | H4: Roof area source | I4: Sizing status | J4: Satellite check (Zara, 7 Oct 2026) | K4: System size (kWp) | N4: Generation (MWh/yr) | Q4: Net saving (£/yr) | T4: Simple payback (years) | W4: CO2e avoided (t/yr) | Z4: Flag | AA4: Satellite view
K5: Low | L5: Central | M5: High | N5: Low | O5: Central | P5: High | Q5: Low | R5: Central | S5: High | T5: Low | U5: Central | V5: High | W5: Low | X5: Central | Y5: High
A6: 1 | B6: Unipart | C6: Top 50 | D6: industrial | E6: 1 | F6: 9774 | G6: =F6 -> 9774 | H6: OpenStreetMap building outline (main building only) | I6: Sized | J6: No panels visible; roof usable: Yes | K6: =IF(Calculations!I5="","",Calculations!I5) -> 660.91788 | L6: =IF(Calculations!I6="","",Calculations!I6) -> 899.208 | M6: =IF(Calculations!I7="","",Calculations!I7) -> 1038.5852 | N6: =IF(Calculations!K5="","",Calculations!K5/1000) -> 609.56456 | O6: =IF(Calculations!K6="","",Calculations!K6/1000) -> 829.33954 | P6: =IF(Calculations!K7="","",Calculations!K7/1000) -> 957.88717 | Q6: =IF(Calculations!T5="","",Calculations!T5) -> 63199.408 | R6: =IF(Calculations!T6="","",Calculations!T6) -> 127021.36 | S6: =IF(Calculations!T7="","",Calculations!T7) -> 187783.94 | T6: =IF(Calculations!W5="","",Calculations!W5) -> 11.503425 | U6: =IF(Calculations!W6="","",Calculations!W6) -> 6.3712683 | V6: =IF(Calculations!W7="","",Calculations!W7) -> 3.871522 | W6: =IF(Calculations!Y5="","",Calculations!Y5) -> 79.828575 | X6: =IF(Calculations!Y6="","",Calculations!Y6) -> 108.61031 | Y6: =IF(Calculations!Y7="","",Calculations!Y7) -> 125.4449 | Z6: =IF($I6="Pending","Sizing pending: angled roof, roof planes not measured (LiDAR or survey needed)",IF(L6>Inputs!$D$15,"Central size above 1 MWp: likely limited by site demand or grid capacity",IF(M6>Inputs!$E$15,"High scenario above 1 MWp: check site demand and grid capacity",""))) -> High scenario above 1 MWp: check site demand and grid capacity | AA6: Satellite
A7: 11 | B7: Unipart Logistics Cowley | C7: Top 50 | D7: warehouse_logistics | E7: 1 | F7: 80278 | G7: =F7 -> 80278 | H7: OpenStreetMap building outline (main building only) | I7: Pending | J7: No panels visible; roof usable: Yes. Note: roofs angled might not be great for solar, array probs smaller than anticipated | K7: =IF(Calculations!I8="","",Calculations!I8) | L7: =IF(Calculations!I9="","",Calculations!I9) | M7: =IF(Calculations!I10="","",Calculations!I10) | N7: =IF(Calculations!K8="","",Calculations!K8/1000) | O7: =IF(Calculations!K9="","",Calculations!K9/1000) | P7: =IF(Calculations!K10="","",Calculations!K10/1000) | Q7: =IF(Calculations!T8="","",Calculations!T8) | R7: =IF(Calculations!T9="","",Calculations!T9) | S7: =IF(Calculations!T10="","",Calculations!T10) | T7: =IF(Calculations!W8="","",Calculations!W8) | U7: =IF(Calculations!W9="","",Calculations!W9) | V7: =IF(Calculations!W10="","",Calculations!W10) | W7: =IF(Calculations!Y8="","",Calculations!Y8) | X7: =IF(Calculations!Y9="","",Calculations!Y9) | Y7: =IF(Calculations!Y10="","",Calculations!Y10) | Z7: =IF($I7="Pending","Sizing pending: angled roof, roof planes not measured (LiDAR or survey needed)",IF(L7>Inputs!$D$15,"Central size above 1 MWp: likely limited by site demand or grid capacity",IF(M7>Inputs!$E$15,"High scenario above 1 MWp: check site demand and grid capacity",""))) -> Sizing pending: angled roof, roof planes not measured (LiDAR or survey needed) | AA7: Satellite
A8: 12 | B8: Sainsbury's | C8: Top 50 | D8: retail | E8: 1 | F8: 8401 | G8: 5488 | H8: Zara Pashov, measured on satellite imagery, 7 Oct 2026 (OSM outline 8,401 m² judged too large) | I8: Sized | J8: No panels visible; roof usable: Yes. Note: I think the roof size is smaller than this estimate, I estimate 5488m2 | K8: =IF(Calculations!I11="","",Calculations!I11) -> 371.09856 | L8: =IF(Calculations!I12="","",Calculations!I12) -> 504.896 | M8: =IF(Calculations!I13="","",Calculations!I13) -> 583.15488 | N8: =IF(Calculations!K11="","",Calculations!K11/1000) -> 342.2642 | O8: =IF(Calculations!K12="","",Calculations!K12/1000) -> 465.66558 | P8: =IF(Calculations!K13="","",Calculations!K13/1000) -> 537.84375 | Q8: =IF(Calculations!T11="","",Calculations!T11) -> 35485.814 | R8: =IF(Calculations!T12="","",Calculations!T12) -> 71321.184 | S8: =IF(Calculations!T13="","",Calculations!T13) -> 105438.74 | T8: =IF(Calculations!W11="","",Calculations!W11) -> 11.503425 | U8: =IF(Calculations!W12="","",Calculations!W12) -> 6.3712683 | V8: =IF(Calculations!W13="","",Calculations!W13) -> 3.871522 | W8: =IF(Calculations!Y11="","",Calculations!Y11) -> 44.82292 | X8: =IF(Calculations!Y12="","",Calculations!Y12) -> 60.983564 | Y8: =IF(Calculations!Y13="","",Calculations!Y13) -> 70.436017 | Z8: =IF($I8="Pending","Sizing pending: angled roof, roof planes not measured (LiDAR or survey needed)",IF(L8>Inputs!$D$15,"Central size above 1 MWp: likely limited by site demand or grid capacity",IF(M8>Inputs!$E$15,"High scenario above 1 MWp: check site demand and grid capacity",""))) | AA8: Satellite
A9: 50 | B9: Ozone Leisure Centre | C9: Top 50 | D9: retail | E9: 1 | F9: 11652 | G9: =F9 -> 11652 | H9: OpenStreetMap building outline (main building only) | I9: Sized | J9: No panels visible; roof usable: Yes | K9: =IF(Calculations!I14="","",Calculations!I14) -> 787.90824 | L9: =IF(Calculations!I15="","",Calculations!I15) -> 1071.984 | M9: =IF(Calculations!I16="","",Calculations!I16) -> 1238.1415 | N9: =IF(Calculations!K14="","",Calculations!K14/1000) -> 726.68777 | O9: =IF(Calculations!K15="","",Calculations!K15/1000) -> 988.69084 | P9: =IF(Calculations!K16="","",Calculations!K16/1000) -> 1141.9379 | Q9: =IF(Calculations!T14="","",Calculations!T14) -> 75342.695 | R9: =IF(Calculations!T15="","",Calculations!T15) -> 151427.56 | S9: =IF(Calculations!T16="","",Calculations!T16) -> 223865.2 | T9: =IF(Calculations!W14="","",Calculations!W14) -> 11.503425 | U9: =IF(Calculations!W15="","",Calculations!W15) -> 6.3712683 | V9: =IF(Calculations!W16="","",Calculations!W16) -> 3.871522 | W9: =IF(Calculations!Y14="","",Calculations!Y14) -> 95.16703 | X9: =IF(Calculations!Y15="","",Calculations!Y15) -> 129.47895 | Y9: =IF(Calculations!Y16="","",Calculations!Y16) -> 149.54819 | Z9: =IF($I9="Pending","Sizing pending: angled roof, roof planes not measured (LiDAR or survey needed)",IF(L9>Inputs!$D$15,"Central size above 1 MWp: likely limited by site demand or grid capacity",IF(M9>Inputs!$E$15,"High scenario above 1 MWp: check site demand and grid capacity",""))) -> Central size above 1 MWp: likely limited by site demand or grid capacity | AA9: Satellite
A10: 26 | B10: Kassam Stadium | C10: Top 50 | D10: hospitality_leisure | E10: 3 | F10: 5428 | G10: =F10 -> 5428 | H10: OpenStreetMap building outline (main building only) | I10: Sized | J10: No panels visible; roof usable: Yes | K10: =IF(Calculations!I17="","",Calculations!I17) -> 367.04136 | L10: =IF(Calculations!I18="","",Calculations!I18) -> 499.376 | M10: =IF(Calculations!I19="","",Calculations!I19) -> 576.77928 | N10: =IF(Calculations!K17="","",Calculations!K17/1000) -> 338.52225 | O10: =IF(Calculations!K18="","",Calculations!K18/1000) -> 460.57448 | P10: =IF(Calculations!K19="","",Calculations!K19/1000) -> 531.96353 | Q10: =IF(Calculations!T17="","",Calculations!T17) -> 35097.85 | R10: =IF(Calculations!T18="","",Calculations!T18) -> 70541.433 | S10: =IF(Calculations!T19="","",Calculations!T19) -> 104285.99 | T10: =IF(Calculations!W17="","",Calculations!W17) -> 11.503425 | U10: =IF(Calculations!W18="","",Calculations!W18) -> 6.3712683 | V10: =IF(Calculations!W19="","",Calculations!W19) -> 3.871522 | W10: =IF(Calculations!Y17="","",Calculations!Y17) -> 44.332873 | X10: =IF(Calculations!Y18="","",Calculations!Y18) -> 60.316835 | Y10: =IF(Calculations!Y19="","",Calculations!Y19) -> 69.665944 | Z10: =IF($I10="Pending","Sizing pending: angled roof, roof planes not measured (LiDAR or survey needed)",IF(L10>Inputs!$D$15,"Central size above 1 MWp: likely limited by site demand or grid capacity",IF(M10>Inputs!$E$15,"High scenario above 1 MWp: check site demand and grid capacity",""))) | AA10: Satellite
A11: 13 | B11: Holiday Inn | C11: Top 50 | D11: untagged_large_no_zone | E11: 1 | F11: 4424 | G11: =F11 -> 4424 | H11: OpenStreetMap building outline (main building only) | I11: Sized | J11: No panels visible; roof usable: Yes | K11: =IF(Calculations!I20="","",Calculations!I20) -> 299.15088 | L11: =IF(Calculations!I21="","",Calculations!I21) -> 407.008 | M11: =IF(Calculations!I22="","",Calculations!I22) -> 470.09424 | N11: =IF(Calculations!K20="","",Calculations!K20/1000) -> 275.90686 | O11: =IF(Calculations!K21="","",Calculations!K21/1000) -> 375.38348 | P11: =IF(Calculations!K22="","",Calculations!K22/1000) -> 433.56792 | Q11: =IF(Calculations!T20="","",Calculations!T20) -> 28605.912 | R11: =IF(Calculations!T21="","",Calculations!T21) -> 57493.607 | S11: =IF(Calculations!T22="","",Calculations!T22) -> 84996.538 | T11: =IF(Calculations!W20="","",Calculations!W20) -> 11.503425 | U11: =IF(Calculations!W21="","",Calculations!W21) -> 6.3712683 | V11: =IF(Calculations!W22="","",Calculations!W22) -> 3.871522 | W11: =IF(Calculations!Y20="","",Calculations!Y20) -> 36.132762 | X11: =IF(Calculations!Y21="","",Calculations!Y21) -> 49.16022 | Y11: =IF(Calculations!Y22="","",Calculations!Y22) -> 56.780054 | Z11: =IF($I11="Pending","Sizing pending: angled roof, roof planes not measured (LiDAR or survey needed)",IF(L11>Inputs!$D$15,"Central size above 1 MWp: likely limited by site demand or grid capacity",IF(M11>Inputs!$E$15,"High scenario above 1 MWp: check site demand and grid capacity",""))) | AA11: Satellite
A12: 24 | B12: The Oxford Academy | C12: Top 50 | D12: education | E12: 3 | F12: 9070 | G12: =F12 -> 9070 | H12: OpenStreetMap building outline (main building only) | I12: Sized | J12: No panels visible; roof usable: Yes | K12: =IF(Calculations!I23="","",Calculations!I23) -> 613.3134 | L12: =IF(Calculations!I24="","",Calculations!I24) -> 834.44 | M12: =IF(Calculations!I25="","",Calculations!I25) -> 963.7782 | N12: =IF(Calculations!K23="","",Calculations!K23/1000) -> 565.65895 | O12: =IF(Calculations!K24="","",Calculations!K24/1000) -> 769.60401 | P12: =IF(Calculations!K25="","",Calculations!K25/1000) -> 888.89263 | Q12: =IF(Calculations!T23="","",Calculations!T23) -> 58647.292 | R12: =IF(Calculations!T24="","",Calculations!T24) -> 117872.29 | S12: =IF(Calculations!T25="","",Calculations!T25) -> 174258.27 | T12: =IF(Calculations!W23="","",Calculations!W23) -> 11.503425 | U12: =IF(Calculations!W24="","",Calculations!W24) -> 6.3712683 | V12: =IF(Calculations!W25="","",Calculations!W25) -> 3.871522 | W12: =IF(Calculations!Y23="","",Calculations!Y23) -> 74.078696 | X12: =IF(Calculations!Y24="","",Calculations!Y24) -> 100.78734 | Y12: =IF(Calculations!Y25="","",Calculations!Y25) -> 116.40938 | Z12: =IF($I12="Pending","Sizing pending: angled roof, roof planes not measured (LiDAR or survey needed)",IF(L12>Inputs!$D$15,"Central size above 1 MWp: likely limited by site demand or grid capacity",IF(M12>Inputs!$E$15,"High scenario above 1 MWp: check site demand and grid capacity",""))) | AA12: Satellite
A13: 28 | B13: Oxford Telephone Exchange | C13: Top 50 | D13: untagged_in_commercial_zone | E13: 1 | F13: 3900 | G13: =F13 -> 3900 | H13: OpenStreetMap building outline (main building only) | I13: Sized | J13: No panels visible; roof usable: Yes | K13: =IF(Calculations!I26="","",Calculations!I26) -> 263.718 | L13: =IF(Calculations!I27="","",Calculations!I27) -> 358.8 | M13: =IF(Calculations!I28="","",Calculations!I28) -> 414.414 | N13: =IF(Calculations!K26="","",Calculations!K26/1000) -> 243.22711 | O13: =IF(Calculations!K27="","",Calculations!K27/1000) -> 330.92124 | P13: =IF(Calculations!K28="","",Calculations!K28/1000) -> 382.21403 | Q13: =IF(Calculations!T26="","",Calculations!T26) -> 25217.689 | R13: =IF(Calculations!T27="","",Calculations!T27) -> 50683.786 | S13: =IF(Calculations!T28="","",Calculations!T28) -> 74929.136 | T13: =IF(Calculations!W26="","",Calculations!W26) -> 11.503425 | U13: =IF(Calculations!W27="","",Calculations!W27) -> 6.3712683 | V13: =IF(Calculations!W28="","",Calculations!W28) -> 3.871522 | W13: =IF(Calculations!Y26="","",Calculations!Y26) -> 31.853023 | X13: =IF(Calculations!Y27="","",Calculations!Y27) -> 43.337446 | Y13: =IF(Calculations!Y28="","",Calculations!Y28) -> 50.05475 | Z13: =IF($I13="Pending","Sizing pending: angled roof, roof planes not measured (LiDAR or survey needed)",IF(L13>Inputs!$D$15,"Central size above 1 MWp: likely limited by site demand or grid capacity",IF(M13>Inputs!$E$15,"High scenario above 1 MWp: check site demand and grid capacity",""))) | AA13: Satellite
A14: 5 | B14: Oxford Business Park (OxBio Hub) | C14: Top 50 | D14: untagged_in_commercial_zone | E14: 1 | F14: 3243 | G14: =F14 -> 3243 | H14: OpenStreetMap building outline (main building only) | I14: Sized | J14: No panels visible; roof usable: Yes | K14: =IF(Calculations!I29="","",Calculations!I29) -> 219.29166 | L14: =IF(Calculations!I30="","",Calculations!I30) -> 298.356 | M14: =IF(Calculations!I31="","",Calculations!I31) -> 344.60118 | N14: =IF(Calculations!K29="","",Calculations!K29/1000) -> 202.2527 | O14: =IF(Calculations!K30="","",Calculations!K30/1000) -> 275.17374 | P14: =IF(Calculations!K31="","",Calculations!K31/1000) -> 317.82567 | Q14: =IF(Calculations!T29="","",Calculations!T29) -> 20969.478 | R14: =IF(Calculations!T30="","",Calculations!T30) -> 42145.517 | S14: =IF(Calculations!T31="","",Calculations!T31) -> 62306.459 | T14: =IF(Calculations!W29="","",Calculations!W29) -> 11.503425 | U14: =IF(Calculations!W30="","",Calculations!W30) -> 6.3712683 | V14: =IF(Calculations!W31="","",Calculations!W31) -> 3.871522 | W14: =IF(Calculations!Y29="","",Calculations!Y29) -> 26.487013 | X14: =IF(Calculations!Y30="","",Calculations!Y30) -> 36.036753 | Y14: =IF(Calculations!Y31="","",Calculations!Y31) -> 41.62245 | Z14: =IF($I14="Pending","Sizing pending: angled roof, roof planes not measured (LiDAR or survey needed)",IF(L14>Inputs!$D$15,"Central size above 1 MWp: likely limited by site demand or grid capacity",IF(M14>Inputs!$E$15,"High scenario above 1 MWp: check site demand and grid capacity",""))) | AA14: Satellite
A15: 7 | B15: Oxford Business Park (John Wiley & Sons) | C15: Top 50 | D15: commercial_office | E15: 1 | F15: 2784 | G15: =F15 -> 2784 | H15: OpenStreetMap building outline (main building only) | I15: Sized | J15: No panels visible; roof usable: Yes | K15: =IF(Calculations!I32="","",Calculations!I32) -> 188.25408 | L15: =IF(Calculations!I33="","",Calculations!I33) -> 256.128 | M15: =IF(Calculations!I34="","",Calculations!I34) -> 295.82784 | N15: =IF(Calculations!K32="","",Calculations!K32/1000) -> 173.62674 | O15: =IF(Calculations!K33="","",Calculations!K33/1000) -> 236.22685 | P15: =IF(Calculations!K34="","",Calculations!K34/1000) -> 272.84202 | Q15: =IF(Calculations!T32="","",Calculations!T32) -> 18001.55 | R15: =IF(Calculations!T33="","",Calculations!T33) -> 36180.426 | S15: =IF(Calculations!T34="","",Calculations!T34) -> 53487.876 | T15: =IF(Calculations!W32="","",Calculations!W32) -> 11.503425 | U15: =IF(Calculations!W33="","",Calculations!W33) -> 6.3712683 | V15: =IF(Calculations!W34="","",Calculations!W34) -> 3.871522 | W15: =IF(Calculations!Y32="","",Calculations!Y32) -> 22.738158 | X15: =IF(Calculations!Y33="","",Calculations!Y33) -> 30.936269 | Y15: =IF(Calculations!Y34="","",Calculations!Y34) -> 35.731391 | Z15: =IF($I15="Pending","Sizing pending: angled roof, roof planes not measured (LiDAR or survey needed)",IF(L15>Inputs!$D$15,"Central size above 1 MWp: likely limited by site demand or grid capacity",IF(M15>Inputs!$E$15,"High scenario above 1 MWp: check site demand and grid capacity",""))) | AA15: Satellite
A16: 21 | B16: Wickes | C16: Top 50 | D16: retail | E16: 1 | F16: 2613 | G16: =F16 -> 2613 | H16: OpenStreetMap building outline (main building only) | I16: Sized | J16: No panels visible; roof usable: Yes | K16: =IF(Calculations!I35="","",Calculations!I35) -> 176.69106 | L16: =IF(Calculations!I36="","",Calculations!I36) -> 240.396 | M16: =IF(Calculations!I37="","",Calculations!I37) -> 277.65738 | N16: =IF(Calculations!K35="","",Calculations!K35/1000) -> 162.96216 | O16: =IF(Calculations!K36="","",Calculations!K36/1000) -> 221.71723 | P16: =IF(Calculations!K37="","",Calculations!K37/1000) -> 256.0834 | Q16: =IF(Calculations!T35="","",Calculations!T35) -> 16895.852 | R16: =IF(Calculations!T36="","",Calculations!T36) -> 33958.137 | S16: =IF(Calculations!T37="","",Calculations!T37) -> 50202.521 | T16: =IF(Calculations!W35="","",Calculations!W35) -> 11.503425 | U16: =IF(Calculations!W36="","",Calculations!W36) -> 6.3712683 | V16: =IF(Calculations!W37="","",Calculations!W37) -> 3.871522 | W16: =IF(Calculations!Y35="","",Calculations!Y35) -> 21.341525 | X16: =IF(Calculations!Y36="","",Calculations!Y36) -> 29.036089 | Y16: =IF(Calculations!Y37="","",Calculations!Y37) -> 33.536682 | Z16: =IF($I16="Pending","Sizing pending: angled roof, roof planes not measured (LiDAR or survey needed)",IF(L16>Inputs!$D$15,"Central size above 1 MWp: likely limited by site demand or grid capacity",IF(M16>Inputs!$E$15,"High scenario above 1 MWp: check site demand and grid capacity",""))) | AA16: Satellite
A17: 30 | B17: Storage King Oxford - Self Storage Units | C17: Top 50 | D17: warehouse_logistics | E17: 1 | F17: 3558 | G17: =F17 -> 3558 | H17: OpenStreetMap building outline (main building only) | I17: Sized | J17: No panels visible; roof usable: Yes. Note: no name given, but it is logisitcs | K17: =IF(Calculations!I38="","",Calculations!I38) -> 240.59196 | L17: =IF(Calculations!I39="","",Calculations!I39) -> 327.336 | M17: =IF(Calculations!I40="","",Calculations!I40) -> 378.07308 | N17: =IF(Calculations!K38="","",Calculations!K38/1000) -> 221.89796 | O17: =IF(Calculations!K39="","",Calculations!K39/1000) -> 301.90199 | P17: =IF(Calculations!K40="","",Calculations!K40/1000) -> 348.6968 | Q17: =IF(Calculations!T38="","",Calculations!T38) -> 23006.291 | R17: =IF(Calculations!T39="","",Calculations!T39) -> 46239.208 | S17: =IF(Calculations!T40="","",Calculations!T40) -> 68358.427 | T17: =IF(Calculations!W38="","",Calculations!W38) -> 11.503425 | U17: =IF(Calculations!W39="","",Calculations!W39) -> 6.3712683 | V17: =IF(Calculations!W40="","",Calculations!W40) -> 3.871522 | W17: =IF(Calculations!Y38="","",Calculations!Y38) -> 29.059757 | X17: =IF(Calculations!Y39="","",Calculations!Y39) -> 39.537085 | Y17: =IF(Calculations!Y40="","",Calculations!Y40) -> 45.665333 | Z17: =IF($I17="Pending","Sizing pending: angled roof, roof planes not measured (LiDAR or survey needed)",IF(L17>Inputs!$D$15,"Central size above 1 MWp: likely limited by site demand or grid capacity",IF(M17>Inputs!$E$15,"High scenario above 1 MWp: check site demand and grid capacity",""))) | AA17: Satellite
A18: 44 | B18: Nuffield Trade and Industrial Park (Royal Mail East Oxford Delivery Office) | C18: Top 50 | D18: untagged_in_industrial_zone | E18: 1 | F18: 1897 | G18: =F18 -> 1897 | H18: OpenStreetMap building outline (main building only) | I18: Sized | J18: No panels visible; roof usable: Yes | K18: =IF(Calculations!I41="","",Calculations!I41) -> 128.27514 | L18: =IF(Calculations!I42="","",Calculations!I42) -> 174.524 | M18: =IF(Calculations!I43="","",Calculations!I43) -> 201.57522 | N18: =IF(Calculations!K41="","",Calculations!K41/1000) -> 118.30816 | O18: =IF(Calculations!K42="","",Calculations!K42/1000) -> 160.96349 | P18: =IF(Calculations!K43="","",Calculations!K43/1000) -> 185.91283 | Q18: =IF(Calculations!T41="","",Calculations!T41) -> 12266.142 | R18: =IF(Calculations!T42="","",Calculations!T42) -> 24653.113 | S18: =IF(Calculations!T43="","",Calculations!T43) -> 36446.3 | T18: =IF(Calculations!W41="","",Calculations!W41) -> 11.503425 | U18: =IF(Calculations!W42="","",Calculations!W42) -> 6.3712683 | V18: =IF(Calculations!W43="","",Calculations!W43) -> 3.871522 | W18: =IF(Calculations!Y41="","",Calculations!Y41) -> 15.493637 | X18: =IF(Calculations!Y42="","",Calculations!Y42) -> 21.079778 | Y18: =IF(Calculations!Y43="","",Calculations!Y43) -> 24.347144 | Z18: =IF($I18="Pending","Sizing pending: angled roof, roof planes not measured (LiDAR or survey needed)",IF(L18>Inputs!$D$15,"Central size above 1 MWp: likely limited by site demand or grid capacity",IF(M18>Inputs!$E$15,"High scenario above 1 MWp: check site demand and grid capacity",""))) | AA18: Satellite
A19: 39 | B19: Unicol Engineering | C19: Top 50 | D19: commercial_office | E19: 1 | F19: 1652 | G19: =F19 -> 1652 | H19: OpenStreetMap building outline (main building only) | I19: Sized | J19: No panels visible; roof usable: Yes | K19: =IF(Calculations!I44="","",Calculations!I44) -> 111.70824 | L19: =IF(Calculations!I45="","",Calculations!I45) -> 151.984 | M19: =IF(Calculations!I46="","",Calculations!I46) -> 175.54152 | N19: =IF(Calculations!K44="","",Calculations!K44/1000) -> 103.02851 | O19: =IF(Calculations!K45="","",Calculations!K45/1000) -> 140.17484 | P19: =IF(Calculations!K46="","",Calculations!K46/1000) -> 161.90194 | Q19: =IF(Calculations!T44="","",Calculations!T44) -> 10681.954 | R19: =IF(Calculations!T45="","",Calculations!T45) -> 21469.132 | S19: =IF(Calculations!T46="","",Calculations!T46) -> 31739.214 | T19: =IF(Calculations!W44="","",Calculations!W44) -> 11.503425 | U19: =IF(Calculations!W45="","",Calculations!W45) -> 6.3712683 | V19: =IF(Calculations!W46="","",Calculations!W46) -> 3.871522 | W19: =IF(Calculations!Y44="","",Calculations!Y44) -> 13.492614 | X19: =IF(Calculations!Y45="","",Calculations!Y45) -> 18.357297 | Y19: =IF(Calculations!Y46="","",Calculations!Y46) -> 21.202679 | Z19: =IF($I19="Pending","Sizing pending: angled roof, roof planes not measured (LiDAR or survey needed)",IF(L19>Inputs!$D$15,"Central size above 1 MWp: likely limited by site demand or grid capacity",IF(M19>Inputs!$E$15,"High scenario above 1 MWp: check site demand and grid capacity",""))) | AA19: Satellite
A20: 40 | B20: Magdalen Centre (Sherrington Buidling) | C20: Top 50 | D20: commercial_office | E20: 1 | F20: 2351 | G20: =F20 -> 2351 | H20: OpenStreetMap building outline (main building only) | I20: Sized | J20: No panels visible; roof usable: Yes | K20: =IF(Calculations!I47="","",Calculations!I47) -> 158.97462 | L20: =IF(Calculations!I48="","",Calculations!I48) -> 216.292 | M20: =IF(Calculations!I49="","",Calculations!I49) -> 249.81726 | N20: =IF(Calculations!K47="","",Calculations!K47/1000) -> 146.62229 | O20: =IF(Calculations!K48="","",Calculations!K48/1000) -> 199.48611 | P20: =IF(Calculations!K49="","",Calculations!K49/1000) -> 230.40646 | Q20: =IF(Calculations!T47="","",Calculations!T47) -> 15201.74 | R20: =IF(Calculations!T48="","",Calculations!T48) -> 30553.226 | S20: =IF(Calculations!T49="","",Calculations!T49) -> 45168.82 | T20: =IF(Calculations!W47="","",Calculations!W47) -> 11.503425 | U20: =IF(Calculations!W48="","",Calculations!W48) -> 6.3712683 | V20: =IF(Calculations!W49="","",Calculations!W49) -> 3.871522 | W20: =IF(Calculations!Y47="","",Calculations!Y47) -> 19.201655 | X20: =IF(Calculations!Y48="","",Calculations!Y48) -> 26.124701 | Y20: =IF(Calculations!Y49="","",Calculations!Y49) -> 30.17403 | Z20: =IF($I20="Pending","Sizing pending: angled roof, roof planes not measured (LiDAR or survey needed)",IF(L20>Inputs!$D$15,"Central size above 1 MWp: likely limited by site demand or grid capacity",IF(M20>Inputs!$E$15,"High scenario above 1 MWp: check site demand and grid capacity",""))) | AA20: Satellite
A21: 22 | B21: Sandhills Community Primary School | C21: Top 50 | D21: education | E21: 1 | F21: 2542 | G21: =F21 -> 2542 | H21: OpenStreetMap building outline (main building only) | I21: Sized | J21: No panels visible; roof usable: Yes | K21: =IF(Calculations!I50="","",Calculations!I50) -> 171.89004 | L21: =IF(Calculations!I51="","",Calculations!I51) -> 233.864 | M21: =IF(Calculations!I52="","",Calculations!I52) -> 270.11292 | N21: =IF(Calculations!K50="","",Calculations!K50/1000) -> 158.53418 | O21: =IF(Calculations!K51="","",Calculations!K51/1000) -> 215.69277 | P21: =IF(Calculations!K52="","",Calculations!K52/1000) -> 249.12515 | Q21: =IF(Calculations!T50="","",Calculations!T50) -> 16436.76 | R21: =IF(Calculations!T51="","",Calculations!T51) -> 33035.432 | S21: =IF(Calculations!T52="","",Calculations!T52) -> 48838.427 | T21: =IF(Calculations!W50="","",Calculations!W50) -> 11.503425 | U21: =IF(Calculations!W51="","",Calculations!W51) -> 6.3712683 | V21: =IF(Calculations!W52="","",Calculations!W52) -> 3.871522 | W21: =IF(Calculations!Y50="","",Calculations!Y50) -> 20.761637 | X21: =IF(Calculations!Y51="","",Calculations!Y51) -> 28.247125 | Y21: =IF(Calculations!Y52="","",Calculations!Y52) -> 32.625429 | Z21: =IF($I21="Pending","Sizing pending: angled roof, roof planes not measured (LiDAR or survey needed)",IF(L21>Inputs!$D$15,"Central size above 1 MWp: likely limited by site demand or grid capacity",IF(M21>Inputs!$E$15,"High scenario above 1 MWp: check site demand and grid capacity",""))) | AA21: Satellite
A22: 99 | B22: Oxford Retail Park (TESCO SUPERSTORE) | C22: Large roofs | D22: retail | E22: 1 | F22: 6954 | G22: =F22 -> 6954 | H22: OpenStreetMap building outline (main building only) | I22: Sized | J22: No panels visible; roof usable: Yes | K22: =IF(Calculations!I53="","",Calculations!I53) -> 470.22948 | L22: =IF(Calculations!I54="","",Calculations!I54) -> 639.768 | M22: =IF(Calculations!I55="","",Calculations!I55) -> 738.93204 | N22: =IF(Calculations!K53="","",Calculations!K53/1000) -> 433.69265 | O22: =IF(Calculations!K54="","",Calculations!K54/1000) -> 590.05803 | P22: =IF(Calculations!K55="","",Calculations!K55/1000) -> 681.51702 | Q22: =IF(Calculations!T53="","",Calculations!T53) -> 44965.079 | R22: =IF(Calculations!T54="","",Calculations!T54) -> 90373.089 | S22: =IF(Calculations!T55="","",Calculations!T55) -> 133604.41 | T22: =IF(Calculations!W53="","",Calculations!W53) -> 11.503425 | U22: =IF(Calculations!W54="","",Calculations!W54) -> 6.3712683 | V22: =IF(Calculations!W55="","",Calculations!W55) -> 3.871522 | W22: =IF(Calculations!Y53="","",Calculations!Y53) -> 56.796389 | X22: =IF(Calculations!Y54="","",Calculations!Y54) -> 77.273999 | Y22: =IF(Calculations!Y55="","",Calculations!Y55) -> 89.251469 | Z22: =IF($I22="Pending","Sizing pending: angled roof, roof planes not measured (LiDAR or survey needed)",IF(L22>Inputs!$D$15,"Central size above 1 MWp: likely limited by site demand or grid capacity",IF(M22>Inputs!$E$15,"High scenario above 1 MWp: check site demand and grid capacity",""))) | AA22: Satellite
A23: 103 | B23: Oxford University Press | C23: Large roofs | D23: commercial_office | E23: 7 | F23: 4584 | G23: =F23 -> 4584 | H23: OpenStreetMap building outline (main building only) | I23: Sized | J23: No panels visible; roof usable: Yes | K23: =IF(Calculations!I56="","",Calculations!I56) -> 309.97008 | L23: =IF(Calculations!I57="","",Calculations!I57) -> 421.728 | M23: =IF(Calculations!I58="","",Calculations!I58) -> 487.09584 | N23: =IF(Calculations!K56="","",Calculations!K56/1000) -> 285.8854 | O23: =IF(Calculations!K57="","",Calculations!K57/1000) -> 388.95973 | P23: =IF(Calculations!K58="","",Calculations!K58/1000) -> 449.24849 | Q23: =IF(Calculations!T56="","",Calculations!T56) -> 29640.483 | R23: =IF(Calculations!T57="","",Calculations!T57) -> 59572.942 | S23: =IF(Calculations!T58="","",Calculations!T58) -> 88070.554 | T23: =IF(Calculations!W56="","",Calculations!W56) -> 11.503425 | U23: =IF(Calculations!W57="","",Calculations!W57) -> 6.3712683 | V23: =IF(Calculations!W58="","",Calculations!W58) -> 3.871522 | W23: =IF(Calculations!Y56="","",Calculations!Y56) -> 37.439553 | X23: =IF(Calculations!Y57="","",Calculations!Y57) -> 50.938167 | Y23: =IF(Calculations!Y58="","",Calculations!Y58) -> 58.833583 | Z23: =IF($I23="Pending","Sizing pending: angled roof, roof planes not measured (LiDAR or survey needed)",IF(L23>Inputs!$D$15,"Central size above 1 MWp: likely limited by site demand or grid capacity",IF(M23>Inputs!$E$15,"High scenario above 1 MWp: check site demand and grid capacity",""))) | AA23: Satellite
A24: 61 | B24: Leonardo Royal Hotel Oxford | C24: Large roofs | D24: hospitality_leisure | E24: 2 | F24: 7218 | G24: =F24 -> 7218 | H24: OpenStreetMap building outline (main building only) | I24: Sized | J24: No panels visible; roof usable: Yes | K24: =IF(Calculations!I59="","",Calculations!I59) -> 488.08116 | L24: =IF(Calculations!I60="","",Calculations!I60) -> 664.056 | M24: =IF(Calculations!I61="","",Calculations!I61) -> 766.98468 | N24: =IF(Calculations!K59="","",Calculations!K59/1000) -> 450.15725 | O24: =IF(Calculations!K60="","",Calculations!K60/1000) -> 612.45885 | P24: =IF(Calculations!K61="","",Calculations!K61/1000) -> 707.38997 | Q24: =IF(Calculations!T59="","",Calculations!T59) -> 46672.123 | R24: =IF(Calculations!T60="","",Calculations!T60) -> 93803.991 | S24: =IF(Calculations!T61="","",Calculations!T61) -> 138676.54 | T24: =IF(Calculations!W59="","",Calculations!W59) -> 11.503425 | U24: =IF(Calculations!W60="","",Calculations!W60) -> 6.3712683 | V24: =IF(Calculations!W61="","",Calculations!W61) -> 3.871522 | W24: =IF(Calculations!Y59="","",Calculations!Y59) -> 58.952594 | X24: =IF(Calculations!Y60="","",Calculations!Y60) -> 80.207611 | Y24: =IF(Calculations!Y61="","",Calculations!Y61) -> 92.639791 | Z24: =IF($I24="Pending","Sizing pending: angled roof, roof planes not measured (LiDAR or survey needed)",IF(L24>Inputs!$D$15,"Central size above 1 MWp: likely limited by site demand or grid capacity",IF(M24>Inputs!$E$15,"High scenario above 1 MWp: check site demand and grid capacity",""))) | AA24: Satellite
A25: 52 | B25: The Manor Hospital | C25: Large roofs | D25: health | E25: 1 | F25: 4354 | G25: =F25 -> 4354 | H25: OpenStreetMap building outline (main building only) | I25: Sized | J25: No panels visible; roof usable: Yes | K25: =IF(Calculations!I62="","",Calculations!I62) -> 294.41748 | L25: =IF(Calculations!I63="","",Calculations!I63) -> 400.568 | M25: =IF(Calculations!I64="","",Calculations!I64) -> 462.65604 | N25: =IF(Calculations!K62="","",Calculations!K62/1000) -> 271.54124 | O25: =IF(Calculations!K63="","",Calculations!K63/1000) -> 369.44387 | P25: =IF(Calculations!K64="","",Calculations!K64/1000) -> 426.70767 | Q25: =IF(Calculations!T62="","",Calculations!T62) -> 28153.286 | R25: =IF(Calculations!T63="","",Calculations!T63) -> 56583.898 | S25: =IF(Calculations!T64="","",Calculations!T64) -> 83651.656 | T25: =IF(Calculations!W62="","",Calculations!W62) -> 11.503425 | U25: =IF(Calculations!W63="","",Calculations!W63) -> 6.3712683 | V25: =IF(Calculations!W64="","",Calculations!W64) -> 3.871522 | W25: =IF(Calculations!Y62="","",Calculations!Y62) -> 35.561041 | X25: =IF(Calculations!Y63="","",Calculations!Y63) -> 48.382369 | Y25: =IF(Calculations!Y64="","",Calculations!Y64) -> 55.881636 | Z25: =IF($I25="Pending","Sizing pending: angled roof, roof planes not measured (LiDAR or survey needed)",IF(L25>Inputs!$D$15,"Central size above 1 MWp: likely limited by site demand or grid capacity",IF(M25>Inputs!$E$15,"High scenario above 1 MWp: check site demand and grid capacity",""))) | AA25: Satellite
B26: Total, sized sites | G26: =SUMIF(I6:I25,"Sized",G6:G25) -> 93486 | K26: =SUM(K6:K25) -> 6321.5233 | L26: =SUM(L6:L25) -> 8600.712 | M26: =SUM(M6:M25) -> 9933.8224 | N26: =SUM(N6:N25) -> 5830.341 | O26: =SUM(O6:O25) -> 7932.4367 | P26: =SUM(P6:P25) -> 9161.9644 | Q26: =SUM(Q6:Q25) -> 604487.4 | R26: =SUM(R6:R25) -> 1214929.3 | S26: =SUM(S6:S25) -> 1796109 | W26: =SUM(W6:W25) -> 763.54145 | X26: =SUM(X6:X25) -> 1038.8319 | Y26: =SUM(Y6:Y25) -> 1199.8509
A28: Why payback is the same at every site within a scenario: every input except roof area is the same for all sites (one yield, one self-consumption share, one price, one cost per kWp), and payback does not depend on roof area. Site-specific payback needs site data, above all how much of the solar each site would use itself.

Sheet Calculations
A1: Calculations: every step for every site and scenario (formulas only; inputs come from the Inputs sheet)
A2: Scenario 1 = Low (pessimistic on every input), 2 = Central, 3 = High (optimistic on every input). Each input is picked from the Inputs sheet with INDEX(row, scenario number).
A4: Rank | B4: Site | C4: Scenario | D4: Scenario no. | E4: Sizing status | F4: Roof area used (m²) | G4: Panel cover share f | H4: Power density rho (W/m²) | I4: System size (kWp) | J4: Specific yield Y (kWh/kWp/yr) | K4: Generation (kWh/yr) | L4: Self-consumption s | M4: Used on site (kWh/yr) | N4: Exported (kWh/yr) | O4: Import price (p/kWh) | P4: Export price (p/kWh) | Q4: Gross saving (£/yr) | R4: O&M rate (£/kW/yr) | S4: O&M cost (£/yr) | T4: Net saving (£/yr) | U4: Capital cost rate (£/kWp) | V4: Capital cost (£) | W4: Simple payback (years) | X4: Carbon factor (kg CO2e/kWh) | Y4: CO2e avoided (t/yr)
A5: 1 | B5: Unipart | C5: Low | D5: 1 | E5: =Results!$I$6 -> Sized | F5: =Results!$G$6 -> 9774 | G5: =INDEX(Inputs!$C$5:$E$5,1,$D5) -> 0.294 | H5: =INDEX(Inputs!$C$6:$E$6,1,$D5) -> 230 | I5: =IF($E5="Pending","",F5*G5*H5/1000) -> 660.91788 | J5: =INDEX(Inputs!$C$7:$E$7,1,$D5) -> 922.3 | K5: =IF($E5="Pending","",I5*J5) -> 609564.56 | L5: =INDEX(Inputs!$C$8:$E$8,1,$D5) -> 0.4 | M5: =IF($E5="Pending","",K5*L5) -> 243825.82 | N5: =IF($E5="Pending","",K5*(1-L5)) -> 365738.74 | O5: =INDEX(Inputs!$C$9:$E$9,1,$D5) -> 24.51 | P5: =INDEX(Inputs!$C$10:$E$10,1,$D5) -> 3 | Q5: =IF($E5="Pending","",(M5*O5+N5*P5)/100) -> 70733.872 | R5: =INDEX(Inputs!$C$12:$E$12,1,$D5) -> 11.4 | S5: =IF($E5="Pending","",I5*R5) -> 7534.4638 | T5: =IF($E5="Pending","",Q5-S5) -> 63199.408 | U5: =INDEX(Inputs!$C$11:$E$11,1,$D5) -> 1100 | V5: =IF($E5="Pending","",I5*U5) -> 727009.67 | W5: =IF($E5="Pending","",IF(T5<=0,"No payback",V5/T5)) -> 11.503425 | X5: =INDEX(Inputs!$C$13:$E$13,1,$D5) -> 0.13096 | Y5: =IF($E5="Pending","",K5*X5/1000) -> 79.828575
A6: 1 | B6: Unipart | C6: Central | D6: 2 | E6: =Results!$I$6 -> Sized | F6: =Results!$G$6 -> 9774 | G6: =INDEX(Inputs!$C$5:$E$5,1,$D6) -> 0.4 | H6: =INDEX(Inputs!$C$6:$E$6,1,$D6) -> 230 | I6: =IF($E6="Pending","",F6*G6*H6/1000) -> 899.208 | J6: =INDEX(Inputs!$C$7:$E$7,1,$D6) -> 922.3 | K6: =IF($E6="Pending","",I6*J6) -> 829339.54 | L6: =INDEX(Inputs!$C$8:$E$8,1,$D6) -> 0.6 | M6: =IF($E6="Pending","",K6*L6) -> 497603.72 | N6: =IF($E6="Pending","",K6*(1-L6)) -> 331735.82 | O6: =INDEX(Inputs!$C$9:$E$9,1,$D6) -> 24.51 | P6: =INDEX(Inputs!$C$10:$E$10,1,$D6) -> 4.1 | Q6: =IF($E6="Pending","",(M6*O6+N6*P6)/100) -> 135563.84 | R6: =INDEX(Inputs!$C$12:$E$12,1,$D6) -> 9.5 | S6: =IF($E6="Pending","",I6*R6) -> 8542.476 | T6: =IF($E6="Pending","",Q6-S6) -> 127021.36 | U6: =INDEX(Inputs!$C$11:$E$11,1,$D6) -> 900 | V6: =IF($E6="Pending","",I6*U6) -> 809287.2 | W6: =IF($E6="Pending","",IF(T6<=0,"No payback",V6/T6)) -> 6.3712683 | X6: =INDEX(Inputs!$C$13:$E$13,1,$D6) -> 0.13096 | Y6: =IF($E6="Pending","",K6*X6/1000) -> 108.61031
A7: 1 | B7: Unipart | C7: High | D7: 3 | E7: =Results!$I$6 -> Sized | F7: =Results!$G$6 -> 9774 | G7: =INDEX(Inputs!$C$5:$E$5,1,$D7) -> 0.462 | H7: =INDEX(Inputs!$C$6:$E$6,1,$D7) -> 230 | I7: =IF($E7="Pending","",F7*G7*H7/1000) -> 1038.5852 | J7: =INDEX(Inputs!$C$7:$E$7,1,$D7) -> 922.3 | K7: =IF($E7="Pending","",I7*J7) -> 957887.17 | L7: =INDEX(Inputs!$C$8:$E$8,1,$D7) -> 0.8 | M7: =IF($E7="Pending","",K7*L7) -> 766309.73 | N7: =IF($E7="Pending","",K7*(1-L7)) -> 191577.43 | O7: =INDEX(Inputs!$C$9:$E$9,1,$D7) -> 24.51 | P7: =INDEX(Inputs!$C$10:$E$10,1,$D7) -> 4.1 | Q7: =IF($E7="Pending","",(M7*O7+N7*P7)/100) -> 195677.19 | R7: =INDEX(Inputs!$C$12:$E$12,1,$D7) -> 7.6 | S7: =IF($E7="Pending","",I7*R7) -> 7893.2478 | T7: =IF($E7="Pending","",Q7-S7) -> 187783.94 | U7: =INDEX(Inputs!$C$11:$E$11,1,$D7) -> 700 | V7: =IF($E7="Pending","",I7*U7) -> 727009.67 | W7: =IF($E7="Pending","",IF(T7<=0,"No payback",V7/T7)) -> 3.871522 | X7: =INDEX(Inputs!$C$13:$E$13,1,$D7) -> 0.13096 | Y7: =IF($E7="Pending","",K7*X7/1000) -> 125.4449
A8: 11 | B8: Unipart Logistics Cowley | C8: Low | D8: 1 | E8: =Results!$I$7 -> Pending | F8: =Results!$G$7 -> 80278 | G8: =INDEX(Inputs!$C$5:$E$5,1,$D8) -> 0.294 | H8: =INDEX(Inputs!$C$6:$E$6,1,$D8) -> 230 | I8: =IF($E8="Pending","",F8*G8*H8/1000) | J8: =INDEX(Inputs!$C$7:$E$7,1,$D8) -> 922.3 | K8: =IF($E8="Pending","",I8*J8) | L8: =INDEX(Inputs!$C$8:$E$8,1,$D8) -> 0.4 | M8: =IF($E8="Pending","",K8*L8) | N8: =IF($E8="Pending","",K8*(1-L8)) | O8: =INDEX(Inputs!$C$9:$E$9,1,$D8) -> 24.51 | P8: =INDEX(Inputs!$C$10:$E$10,1,$D8) -> 3 | Q8: =IF($E8="Pending","",(M8*O8+N8*P8)/100) | R8: =INDEX(Inputs!$C$12:$E$12,1,$D8) -> 11.4 | S8: =IF($E8="Pending","",I8*R8) | T8: =IF($E8="Pending","",Q8-S8) | U8: =INDEX(Inputs!$C$11:$E$11,1,$D8) -> 1100 | V8: =IF($E8="Pending","",I8*U8) | W8: =IF($E8="Pending","",IF(T8<=0,"No payback",V8/T8)) | X8: =INDEX(Inputs!$C$13:$E$13,1,$D8) -> 0.13096 | Y8: =IF($E8="Pending","",K8*X8/1000)
A9: 11 | B9: Unipart Logistics Cowley | C9: Central | D9: 2 | E9: =Results!$I$7 -> Pending | F9: =Results!$G$7 -> 80278 | G9: =INDEX(Inputs!$C$5:$E$5,1,$D9) -> 0.4 | H9: =INDEX(Inputs!$C$6:$E$6,1,$D9) -> 230 | I9: =IF($E9="Pending","",F9*G9*H9/1000) | J9: =INDEX(Inputs!$C$7:$E$7,1,$D9) -> 922.3 | K9: =IF($E9="Pending","",I9*J9) | L9: =INDEX(Inputs!$C$8:$E$8,1,$D9) -> 0.6 | M9: =IF($E9="Pending","",K9*L9) | N9: =IF($E9="Pending","",K9*(1-L9)) | O9: =INDEX(Inputs!$C$9:$E$9,1,$D9) -> 24.51 | P9: =INDEX(Inputs!$C$10:$E$10,1,$D9) -> 4.1 | Q9: =IF($E9="Pending","",(M9*O9+N9*P9)/100) | R9: =INDEX(Inputs!$C$12:$E$12,1,$D9) -> 9.5 | S9: =IF($E9="Pending","",I9*R9) | T9: =IF($E9="Pending","",Q9-S9) | U9: =INDEX(Inputs!$C$11:$E$11,1,$D9) -> 900 | V9: =IF($E9="Pending","",I9*U9) | W9: =IF($E9="Pending","",IF(T9<=0,"No payback",V9/T9)) | X9: =INDEX(Inputs!$C$13:$E$13,1,$D9) -> 0.13096 | Y9: =IF($E9="Pending","",K9*X9/1000)
A10: 11 | B10: Unipart Logistics Cowley | C10: High | D10: 3 | E10: =Results!$I$7 -> Pending | F10: =Results!$G$7 -> 80278 | G10: =INDEX(Inputs!$C$5:$E$5,1,$D10) -> 0.462 | H10: =INDEX(Inputs!$C$6:$E$6,1,$D10) -> 230 | I10: =IF($E10="Pending","",F10*G10*H10/1000) | J10: =INDEX(Inputs!$C$7:$E$7,1,$D10) -> 922.3 | K10: =IF($E10="Pending","",I10*J10) | L10: =INDEX(Inputs!$C$8:$E$8,1,$D10) -> 0.8 | M10: =IF($E10="Pending","",K10*L10) | N10: =IF($E10="Pending","",K10*(1-L10)) | O10: =INDEX(Inputs!$C$9:$E$9,1,$D10) -> 24.51 | P10: =INDEX(Inputs!$C$10:$E$10,1,$D10) -> 4.1 | Q10: =IF($E10="Pending","",(M10*O10+N10*P10)/100) | R10: =INDEX(Inputs!$C$12:$E$12,1,$D10) -> 7.6 | S10: =IF($E10="Pending","",I10*R10) | T10: =IF($E10="Pending","",Q10-S10) | U10: =INDEX(Inputs!$C$11:$E$11,1,$D10) -> 700 | V10: =IF($E10="Pending","",I10*U10) | W10: =IF($E10="Pending","",IF(T10<=0,"No payback",V10/T10)) | X10: =INDEX(Inputs!$C$13:$E$13,1,$D10) -> 0.13096 | Y10: =IF($E10="Pending","",K10*X10/1000)
A11: 12 | B11: Sainsbury's | C11: Low | D11: 1 | E11: =Results!$I$8 -> Sized | F11: =Results!$G$8 -> 5488 | G11: =INDEX(Inputs!$C$5:$E$5,1,$D11) -> 0.294 | H11: =INDEX(Inputs!$C$6:$E$6,1,$D11) -> 230 | I11: =IF($E11="Pending","",F11*G11*H11/1000) -> 371.09856 | J11: =INDEX(Inputs!$C$7:$E$7,1,$D11) -> 922.3 | K11: =IF($E11="Pending","",I11*J11) -> 342264.2 | L11: =INDEX(Inputs!$C$8:$E$8,1,$D11) -> 0.4 | M11: =IF($E11="Pending","",K11*L11) -> 136905.68 | N11: =IF($E11="Pending","",K11*(1-L11)) -> 205358.52 | O11: =INDEX(Inputs!$C$9:$E$9,1,$D11) -> 24.51 | P11: =INDEX(Inputs!$C$10:$E$10,1,$D11) -> 3 | Q11: =IF($E11="Pending","",(M11*O11+N11*P11)/100) -> 39716.338 | R11: =INDEX(Inputs!$C$12:$E$12,1,$D11) -> 11.4 | S11: =IF($E11="Pending","",I11*R11) -> 4230.5236 | T11: =IF($E11="Pending","",Q11-S11) -> 35485.814 | U11: =INDEX(Inputs!$C$11:$E$11,1,$D11) -> 1100 | V11: =IF($E11="Pending","",I11*U11) -> 408208.42 | W11: =IF($E11="Pending","",IF(T11<=0,"No payback",V11/T11)) -> 11.503425 | X11: =INDEX(Inputs!$C$13:$E$13,1,$D11) -> 0.13096 | Y11: =IF($E11="Pending","",K11*X11/1000) -> 44.82292
A12: 12 | B12: Sainsbury's | C12: Central | D12: 2 | E12: =Results!$I$8 -> Sized | F12: =Results!$G$8 -> 5488 | G12: =INDEX(Inputs!$C$5:$E$5,1,$D12) -> 0.4 | H12: =INDEX(Inputs!$C$6:$E$6,1,$D12) -> 230 | I12: =IF($E12="Pending","",F12*G12*H12/1000) -> 504.896 | J12: =INDEX(Inputs!$C$7:$E$7,1,$D12) -> 922.3 | K12: =IF($E12="Pending","",I12*J12) -> 465665.58 | L12: =INDEX(Inputs!$C$8:$E$8,1,$D12) -> 0.6 | M12: =IF($E12="Pending","",K12*L12) -> 279399.35 | N12: =IF($E12="Pending","",K12*(1-L12)) -> 186266.23 | O12: =INDEX(Inputs!$C$9:$E$9,1,$D12) -> 24.51 | P12: =INDEX(Inputs!$C$10:$E$10,1,$D12) -> 4.1 | Q12: =IF($E12="Pending","",(M12*O12+N12*P12)/100) -> 76117.696 | R12: =INDEX(Inputs!$C$12:$E$12,1,$D12) -> 9.5 | S12: =IF($E12="Pending","",I12*R12) -> 4796.512 | T12: =IF($E12="Pending","",Q12-S12) -> 71321.184 | U12: =INDEX(Inputs!$C$11:$E$11,1,$D12) -> 900 | V12: =IF($E12="Pending","",I12*U12) -> 454406.4 | W12: =IF($E12="Pending","",IF(T12<=0,"No payback",V12/T12)) -> 6.3712683 | X12: =INDEX(Inputs!$C$13:$E$13,1,$D12) -> 0.13096 | Y12: =IF($E12="Pending","",K12*X12/1000) -> 60.983564
A13: 12 | B13: Sainsbury's | C13: High | D13: 3 | E13: =Results!$I$8 -> Sized | F13: =Results!$G$8 -> 5488 | G13: =INDEX(Inputs!$C$5:$E$5,1,$D13) -> 0.462 | H13: =INDEX(Inputs!$C$6:$E$6,1,$D13) -> 230 | I13: =IF($E13="Pending","",F13*G13*H13/1000) -> 583.15488 | J13: =INDEX(Inputs!$C$7:$E$7,1,$D13) -> 922.3 | K13: =IF($E13="Pending","",I13*J13) -> 537843.75 | L13: =INDEX(Inputs!$C$8:$E$8,1,$D13) -> 0.8 | M13: =IF($E13="Pending","",K13*L13) -> 430275 | N13: =IF($E13="Pending","",K13*(1-L13)) -> 107568.75 | O13: =INDEX(Inputs!$C$9:$E$9,1,$D13) -> 24.51 | P13: =INDEX(Inputs!$C$10:$E$10,1,$D13) -> 4.1 | Q13: =IF($E13="Pending","",(M13*O13+N13*P13)/100) -> 109870.72 | R13: =INDEX(Inputs!$C$12:$E$12,1,$D13) -> 7.6 | S13: =IF($E13="Pending","",I13*R13) -> 4431.9771 | T13: =IF($E13="Pending","",Q13-S13) -> 105438.74 | U13: =INDEX(Inputs!$C$11:$E$11,1,$D13) -> 700 | V13: =IF($E13="Pending","",I13*U13) -> 408208.42 | W13: =IF($E13="Pending","",IF(T13<=0,"No payback",V13/T13)) -> 3.871522 | X13: =INDEX(Inputs!$C$13:$E$13,1,$D13) -> 0.13096 | Y13: =IF($E13="Pending","",K13*X13/1000) -> 70.436017
A14: 50 | B14: Ozone Leisure Centre | C14: Low | D14: 1 | E14: =Results!$I$9 -> Sized | F14: =Results!$G$9 -> 11652 | G14: =INDEX(Inputs!$C$5:$E$5,1,$D14) -> 0.294 | H14: =INDEX(Inputs!$C$6:$E$6,1,$D14) -> 230 | I14: =IF($E14="Pending","",F14*G14*H14/1000) -> 787.90824 | J14: =INDEX(Inputs!$C$7:$E$7,1,$D14) -> 922.3 | K14: =IF($E14="Pending","",I14*J14) -> 726687.77 | L14: =INDEX(Inputs!$C$8:$E$8,1,$D14) -> 0.4 | M14: =IF($E14="Pending","",K14*L14) -> 290675.11 | N14: =IF($E14="Pending","",K14*(1-L14)) -> 436012.66 | O14: =INDEX(Inputs!$C$9:$E$9,1,$D14) -> 24.51 | P14: =INDEX(Inputs!$C$10:$E$10,1,$D14) -> 3 | Q14: =IF($E14="Pending","",(M14*O14+N14*P14)/100) -> 84324.849 | R14: =INDEX(Inputs!$C$12:$E$12,1,$D14) -> 11.4 | S14: =IF($E14="Pending","",I14*R14) -> 8982.1539 | T14: =IF($E14="Pending","",Q14-S14) -> 75342.695 | U14: =INDEX(Inputs!$C$11:$E$11,1,$D14) -> 1100 | V14: =IF($E14="Pending","",I14*U14) -> 866699.06 | W14: =IF($E14="Pending","",IF(T14<=0,"No payback",V14/T14)) -> 11.503425 | X14: =INDEX(Inputs!$C$13:$E$13,1,$D14) -> 0.13096 | Y14: =IF($E14="Pending","",K14*X14/1000) -> 95.16703
A15: 50 | B15: Ozone Leisure Centre | C15: Central | D15: 2 | E15: =Results!$I$9 -> Sized | F15: =Results!$G$9 -> 11652 | G15: =INDEX(Inputs!$C$5:$E$5,1,$D15) -> 0.4 | H15: =INDEX(Inputs!$C$6:$E$6,1,$D15) -> 230 | I15: =IF($E15="Pending","",F15*G15*H15/1000) -> 1071.984 | J15: =INDEX(Inputs!$C$7:$E$7,1,$D15) -> 922.3 | K15: =IF($E15="Pending","",I15*J15) -> 988690.84 | L15: =INDEX(Inputs!$C$8:$E$8,1,$D15) -> 0.6 | M15: =IF($E15="Pending","",K15*L15) -> 593214.51 | N15: =IF($E15="Pending","",K15*(1-L15)) -> 395476.34 | O15: =INDEX(Inputs!$C$9:$E$9,1,$D15) -> 24.51 | P15: =INDEX(Inputs!$C$10:$E$10,1,$D15) -> 4.1 | Q15: =IF($E15="Pending","",(M15*O15+N15*P15)/100) -> 161611.41 | R15: =INDEX(Inputs!$C$12:$E$12,1,$D15) -> 9.5 | S15: =IF($E15="Pending","",I15*R15) -> 10183.848 | T15: =IF($E15="Pending","",Q15-S15) -> 151427.56 | U15: =INDEX(Inputs!$C$11:$E$11,1,$D15) -> 900 | V15: =IF($E15="Pending","",I15*U15) -> 964785.6 | W15: =IF($E15="Pending","",IF(T15<=0,"No payback",V15/T15)) -> 6.3712683 | X15: =INDEX(Inputs!$C$13:$E$13,1,$D15) -> 0.13096 | Y15: =IF($E15="Pending","",K15*X15/1000) -> 129.47895
A16: 50 | B16: Ozone Leisure Centre | C16: High | D16: 3 | E16: =Results!$I$9 -> Sized | F16: =Results!$G$9 -> 11652 | G16: =INDEX(Inputs!$C$5:$E$5,1,$D16) -> 0.462 | H16: =INDEX(Inputs!$C$6:$E$6,1,$D16) -> 230 | I16: =IF($E16="Pending","",F16*G16*H16/1000) -> 1238.1415 | J16: =INDEX(Inputs!$C$7:$E$7,1,$D16) -> 922.3 | K16: =IF($E16="Pending","",I16*J16) -> 1141937.9 | L16: =INDEX(Inputs!$C$8:$E$8,1,$D16) -> 0.8 | M16: =IF($E16="Pending","",K16*L16) -> 913550.34 | N16: =IF($E16="Pending","",K16*(1-L16)) -> 228387.58 | O16: =INDEX(Inputs!$C$9:$E$9,1,$D16) -> 24.51 | P16: =INDEX(Inputs!$C$10:$E$10,1,$D16) -> 4.1 | Q16: =IF($E16="Pending","",(M16*O16+N16*P16)/100) -> 233275.08 | R16: =INDEX(Inputs!$C$12:$E$12,1,$D16) -> 7.6 | S16: =IF($E16="Pending","",I16*R16) -> 9409.8756 | T16: =IF($E16="Pending","",Q16-S16) -> 223865.2 | U16: =INDEX(Inputs!$C$11:$E$11,1,$D16) -> 700 | V16: =IF($E16="Pending","",I16*U16) -> 866699.06 | W16: =IF($E16="Pending","",IF(T16<=0,"No payback",V16/T16)) -> 3.871522 | X16: =INDEX(Inputs!$C$13:$E$13,1,$D16) -> 0.13096 | Y16: =IF($E16="Pending","",K16*X16/1000) -> 149.54819
A17: 26 | B17: Kassam Stadium | C17: Low | D17: 1 | E17: =Results!$I$10 -> Sized | F17: =Results!$G$10 -> 5428 | G17: =INDEX(Inputs!$C$5:$E$5,1,$D17) -> 0.294 | H17: =INDEX(Inputs!$C$6:$E$6,1,$D17) -> 230 | I17: =IF($E17="Pending","",F17*G17*H17/1000) -> 367.04136 | J17: =INDEX(Inputs!$C$7:$E$7,1,$D17) -> 922.3 | K17: =IF($E17="Pending","",I17*J17) -> 338522.25 | L17: =INDEX(Inputs!$C$8:$E$8,1,$D17) -> 0.4 | M17: =IF($E17="Pending","",K17*L17) -> 135408.9 | N17: =IF($E17="Pending","",K17*(1-L17)) -> 203113.35 | O17: =INDEX(Inputs!$C$9:$E$9,1,$D17) -> 24.51 | P17: =INDEX(Inputs!$C$10:$E$10,1,$D17) -> 3 | Q17: =IF($E17="Pending","",(M17*O17+N17*P17)/100) -> 39282.121 | R17: =INDEX(Inputs!$C$12:$E$12,1,$D17) -> 11.4 | S17: =IF($E17="Pending","",I17*R17) -> 4184.2715 | T17: =IF($E17="Pending","",Q17-S17) -> 35097.85 | U17: =INDEX(Inputs!$C$11:$E$11,1,$D17) -> 1100 | V17: =IF($E17="Pending","",I17*U17) -> 403745.5 | W17: =IF($E17="Pending","",IF(T17<=0,"No payback",V17/T17)) -> 11.503425 | X17: =INDEX(Inputs!$C$13:$E$13,1,$D17) -> 0.13096 | Y17: =IF($E17="Pending","",K17*X17/1000) -> 44.332873
A18: 26 | B18: Kassam Stadium | C18: Central | D18: 2 | E18: =Results!$I$10 -> Sized | F18: =Results!$G$10 -> 5428 | G18: =INDEX(Inputs!$C$5:$E$5,1,$D18) -> 0.4 | H18: =INDEX(Inputs!$C$6:$E$6,1,$D18) -> 230 | I18: =IF($E18="Pending","",F18*G18*H18/1000) -> 499.376 | J18: =INDEX(Inputs!$C$7:$E$7,1,$D18) -> 922.3 | K18: =IF($E18="Pending","",I18*J18) -> 460574.48 | L18: =INDEX(Inputs!$C$8:$E$8,1,$D18) -> 0.6 | M18: =IF($E18="Pending","",K18*L18) -> 276344.69 | N18: =IF($E18="Pending","",K18*(1-L18)) -> 184229.79 | O18: =INDEX(Inputs!$C$9:$E$9,1,$D18) -> 24.51 | P18: =INDEX(Inputs!$C$10:$E$10,1,$D18) -> 4.1 | Q18: =IF($E18="Pending","",(M18*O18+N18*P18)/100) -> 75285.505 | R18: =INDEX(Inputs!$C$12:$E$12,1,$D18) -> 9.5 | S18: =IF($E18="Pending","",I18*R18) -> 4744.072 | T18: =IF($E18="Pending","",Q18-S18) -> 70541.433 | U18: =INDEX(Inputs!$C$11:$E$11,1,$D18) -> 900 | V18: =IF($E18="Pending","",I18*U18) -> 449438.4 | W18: =IF($E18="Pending","",IF(T18<=0,"No payback",V18/T18)) -> 6.3712683 | X18: =INDEX(Inputs!$C$13:$E$13,1,$D18) -> 0.13096 | Y18: =IF($E18="Pending","",K18*X18/1000) -> 60.316835
A19: 26 | B19: Kassam Stadium | C19: High | D19: 3 | E19: =Results!$I$10 -> Sized | F19: =Results!$G$10 -> 5428 | G19: =INDEX(Inputs!$C$5:$E$5,1,$D19) -> 0.462 | H19: =INDEX(Inputs!$C$6:$E$6,1,$D19) -> 230 | I19: =IF($E19="Pending","",F19*G19*H19/1000) -> 576.77928 | J19: =INDEX(Inputs!$C$7:$E$7,1,$D19) -> 922.3 | K19: =IF($E19="Pending","",I19*J19) -> 531963.53 | L19: =INDEX(Inputs!$C$8:$E$8,1,$D19) -> 0.8 | M19: =IF($E19="Pending","",K19*L19) -> 425570.82 | N19: =IF($E19="Pending","",K19*(1-L19)) -> 106392.71 | O19: =INDEX(Inputs!$C$9:$E$9,1,$D19) -> 24.51 | P19: =INDEX(Inputs!$C$10:$E$10,1,$D19) -> 4.1 | Q19: =IF($E19="Pending","",(M19*O19+N19*P19)/100) -> 108669.51 | R19: =INDEX(Inputs!$C$12:$E$12,1,$D19) -> 7.6 | S19: =IF($E19="Pending","",I19*R19) -> 4383.5225 | T19: =IF($E19="Pending","",Q19-S19) -> 104285.99 | U19: =INDEX(Inputs!$C$11:$E$11,1,$D19) -> 700 | V19: =IF($E19="Pending","",I19*U19) -> 403745.5 | W19: =IF($E19="Pending","",IF(T19<=0,"No payback",V19/T19)) -> 3.871522 | X19: =INDEX(Inputs!$C$13:$E$13,1,$D19) -> 0.13096 | Y19: =IF($E19="Pending","",K19*X19/1000) -> 69.665944
A20: 13 | B20: Holiday Inn | C20: Low | D20: 1 | E20: =Results!$I$11 -> Sized | F20: =Results!$G$11 -> 4424 | G20: =INDEX(Inputs!$C$5:$E$5,1,$D20) -> 0.294 | H20: =INDEX(Inputs!$C$6:$E$6,1,$D20) -> 230 | I20: =IF($E20="Pending","",F20*G20*H20/1000) -> 299.15088 | J20: =INDEX(Inputs!$C$7:$E$7,1,$D20) -> 922.3 | K20: =IF($E20="Pending","",I20*J20) -> 275906.86 | L20: =INDEX(Inputs!$C$8:$E$8,1,$D20) -> 0.4 | M20: =IF($E20="Pending","",K20*L20) -> 110362.74 | N20: =IF($E20="Pending","",K20*(1-L20)) -> 165544.11 | O20: =INDEX(Inputs!$C$9:$E$9,1,$D20) -> 24.51 | P20: =INDEX(Inputs!$C$10:$E$10,1,$D20) -> 3 | Q20: =IF($E20="Pending","",(M20*O20+N20*P20)/100) -> 32016.232 | R20: =INDEX(Inputs!$C$12:$E$12,1,$D20) -> 11.4 | S20: =IF($E20="Pending","",I20*R20) -> 3410.32 | T20: =IF($E20="Pending","",Q20-S20) -> 28605.912 | U20: =INDEX(Inputs!$C$11:$E$11,1,$D20) -> 1100 | V20: =IF($E20="Pending","",I20*U20) -> 329065.97 | W20: =IF($E20="Pending","",IF(T20<=0,"No payback",V20/T20)) -> 11.503425 | X20: =INDEX(Inputs!$C$13:$E$13,1,$D20) -> 0.13096 | Y20: =IF($E20="Pending","",K20*X20/1000) -> 36.132762
A21: 13 | B21: Holiday Inn | C21: Central | D21: 2 | E21: =Results!$I$11 -> Sized | F21: =Results!$G$11 -> 4424 | G21: =INDEX(Inputs!$C$5:$E$5,1,$D21) -> 0.4 | H21: =INDEX(Inputs!$C$6:$E$6,1,$D21) -> 230 | I21: =IF($E21="Pending","",F21*G21*H21/1000) -> 407.008 | J21: =INDEX(Inputs!$C$7:$E$7,1,$D21) -> 922.3 | K21: =IF($E21="Pending","",I21*J21) -> 375383.48 | L21: =INDEX(Inputs!$C$8:$E$8,1,$D21) -> 0.6 | M21: =IF($E21="Pending","",K21*L21) -> 225230.09 | N21: =IF($E21="Pending","",K21*(1-L21)) -> 150153.39 | O21: =INDEX(Inputs!$C$9:$E$9,1,$D21) -> 24.51 | P21: =INDEX(Inputs!$C$10:$E$10,1,$D21) -> 4.1 | Q21: =IF($E21="Pending","",(M21*O21+N21*P21)/100) -> 61360.183 | R21: =INDEX(Inputs!$C$12:$E$12,1,$D21) -> 9.5 | S21: =IF($E21="Pending","",I21*R21) -> 3866.576 | T21: =IF($E21="Pending","",Q21-S21) -> 57493.607 | U21: =INDEX(Inputs!$C$11:$E$11,1,$D21) -> 900 | V21: =IF($E21="Pending","",I21*U21) -> 366307.2 | W21: =IF($E21="Pending","",IF(T21<=0,"No payback",V21/T21)) -> 6.3712683 | X21: =INDEX(Inputs!$C$13:$E$13,1,$D21) -> 0.13096 | Y21: =IF($E21="Pending","",K21*X21/1000) -> 49.16022
A22: 13 | B22: Holiday Inn | C22: High | D22: 3 | E22: =Results!$I$11 -> Sized | F22: =Results!$G$11 -> 4424 | G22: =INDEX(Inputs!$C$5:$E$5,1,$D22) -> 0.462 | H22: =INDEX(Inputs!$C$6:$E$6,1,$D22) -> 230 | I22: =IF($E22="Pending","",F22*G22*H22/1000) -> 470.09424 | J22: =INDEX(Inputs!$C$7:$E$7,1,$D22) -> 922.3 | K22: =IF($E22="Pending","",I22*J22) -> 433567.92 | L22: =INDEX(Inputs!$C$8:$E$8,1,$D22) -> 0.8 | M22: =IF($E22="Pending","",K22*L22) -> 346854.33 | N22: =IF($E22="Pending","",K22*(1-L22)) -> 86713.584 | O22: =INDEX(Inputs!$C$9:$E$9,1,$D22) -> 24.51 | P22: =INDEX(Inputs!$C$10:$E$10,1,$D22) -> 4.1 | Q22: =IF($E22="Pending","",(M22*O22+N22*P22)/100) -> 88569.254 | R22: =INDEX(Inputs!$C$12:$E$12,1,$D22) -> 7.6 | S22: =IF($E22="Pending","",I22*R22) -> 3572.7162 | T22: =IF($E22="Pending","",Q22-S22) -> 84996.538 | U22: =INDEX(Inputs!$C$11:$E$11,1,$D22) -> 700 | V22: =IF($E22="Pending","",I22*U22) -> 329065.97 | W22: =IF($E22="Pending","",IF(T22<=0,"No payback",V22/T22)) -> 3.871522 | X22: =INDEX(Inputs!$C$13:$E$13,1,$D22) -> 0.13096 | Y22: =IF($E22="Pending","",K22*X22/1000) -> 56.780054
A23: 24 | B23: The Oxford Academy | C23: Low | D23: 1 | E23: =Results!$I$12 -> Sized | F23: =Results!$G$12 -> 9070 | G23: =INDEX(Inputs!$C$5:$E$5,1,$D23) -> 0.294 | H23: =INDEX(Inputs!$C$6:$E$6,1,$D23) -> 230 | I23: =IF($E23="Pending","",F23*G23*H23/1000) -> 613.3134 | J23: =INDEX(Inputs!$C$7:$E$7,1,$D23) -> 922.3 | K23: =IF($E23="Pending","",I23*J23) -> 565658.95 | L23: =INDEX(Inputs!$C$8:$E$8,1,$D23) -> 0.4 | M23: =IF($E23="Pending","",K23*L23) -> 226263.58 | N23: =IF($E23="Pending","",K23*(1-L23)) -> 339395.37 | O23: =INDEX(Inputs!$C$9:$E$9,1,$D23) -> 24.51 | P23: =INDEX(Inputs!$C$10:$E$10,1,$D23) -> 3 | Q23: =IF($E23="Pending","",(M23*O23+N23*P23)/100) -> 65639.064 | R23: =INDEX(Inputs!$C$12:$E$12,1,$D23) -> 11.4 | S23: =IF($E23="Pending","",I23*R23) -> 6991.7728 | T23: =IF($E23="Pending","",Q23-S23) -> 58647.292 | U23: =INDEX(Inputs!$C$11:$E$11,1,$D23) -> 1100 | V23: =IF($E23="Pending","",I23*U23) -> 674644.74 | W23: =IF($E23="Pending","",IF(T23<=0,"No payback",V23/T23)) -> 11.503425 | X23: =INDEX(Inputs!$C$13:$E$13,1,$D23) -> 0.13096 | Y23: =IF($E23="Pending","",K23*X23/1000) -> 74.078696
A24: 24 | B24: The Oxford Academy | C24: Central | D24: 2 | E24: =Results!$I$12 -> Sized | F24: =Results!$G$12 -> 9070 | G24: =INDEX(Inputs!$C$5:$E$5,1,$D24) -> 0.4 | H24: =INDEX(Inputs!$C$6:$E$6,1,$D24) -> 230 | I24: =IF($E24="Pending","",F24*G24*H24/1000) -> 834.44 | J24: =INDEX(Inputs!$C$7:$E$7,1,$D24) -> 922.3 | K24: =IF($E24="Pending","",I24*J24) -> 769604.01 | L24: =INDEX(Inputs!$C$8:$E$8,1,$D24) -> 0.6 | M24: =IF($E24="Pending","",K24*L24) -> 461762.41 | N24: =IF($E24="Pending","",K24*(1-L24)) -> 307841.6 | O24: =INDEX(Inputs!$C$9:$E$9,1,$D24) -> 24.51 | P24: =INDEX(Inputs!$C$10:$E$10,1,$D24) -> 4.1 | Q24: =IF($E24="Pending","",(M24*O24+N24*P24)/100) -> 125799.47 | R24: =INDEX(Inputs!$C$12:$E$12,1,$D24) -> 9.5 | S24: =IF($E24="Pending","",I24*R24) -> 7927.18 | T24: =IF($E24="Pending","",Q24-S24) -> 117872.29 | U24: =INDEX(Inputs!$C$11:$E$11,1,$D24) -> 900 | V24: =IF($E24="Pending","",I24*U24) -> 750996 | W24: =IF($E24="Pending","",IF(T24<=0,"No payback",V24/T24)) -> 6.3712683 | X24: =INDEX(Inputs!$C$13:$E$13,1,$D24) -> 0.13096 | Y24: =IF($E24="Pending","",K24*X24/1000) -> 100.78734
A25: 24 | B25: The Oxford Academy | C25: High | D25: 3 | E25: =Results!$I$12 -> Sized | F25: =Results!$G$12 -> 9070 | G25: =INDEX(Inputs!$C$5:$E$5,1,$D25) -> 0.462 | H25: =INDEX(Inputs!$C$6:$E$6,1,$D25) -> 230 | I25: =IF($E25="Pending","",F25*G25*H25/1000) -> 963.7782 | J25: =INDEX(Inputs!$C$7:$E$7,1,$D25) -> 922.3 | K25: =IF($E25="Pending","",I25*J25) -> 888892.63 | L25: =INDEX(Inputs!$C$8:$E$8,1,$D25) -> 0.8 | M25: =IF($E25="Pending","",K25*L25) -> 711114.11 | N25: =IF($E25="Pending","",K25*(1-L25)) -> 177778.53 | O25: =INDEX(Inputs!$C$9:$E$9,1,$D25) -> 24.51 | P25: =INDEX(Inputs!$C$10:$E$10,1,$D25) -> 4.1 | Q25: =IF($E25="Pending","",(M25*O25+N25*P25)/100) -> 181582.99 | R25: =INDEX(Inputs!$C$12:$E$12,1,$D25) -> 7.6 | S25: =IF($E25="Pending","",I25*R25) -> 7324.7143 | T25: =IF($E25="Pending","",Q25-S25) -> 174258.27 | U25: =INDEX(Inputs!$C$11:$E$11,1,$D25) -> 700 | V25: =IF($E25="Pending","",I25*U25) -> 674644.74 | W25: =IF($E25="Pending","",IF(T25<=0,"No payback",V25/T25)) -> 3.871522 | X25: =INDEX(Inputs!$C$13:$E$13,1,$D25) -> 0.13096 | Y25: =IF($E25="Pending","",K25*X25/1000) -> 116.40938
A26: 28 | B26: Oxford Telephone Exchange | C26: Low | D26: 1 | E26: =Results!$I$13 -> Sized | F26: =Results!$G$13 -> 3900 | G26: =INDEX(Inputs!$C$5:$E$5,1,$D26) -> 0.294 | H26: =INDEX(Inputs!$C$6:$E$6,1,$D26) -> 230 | I26: =IF($E26="Pending","",F26*G26*H26/1000) -> 263.718 | J26: =INDEX(Inputs!$C$7:$E$7,1,$D26) -> 922.3 | K26: =IF($E26="Pending","",I26*J26) -> 243227.11 | L26: =INDEX(Inputs!$C$8:$E$8,1,$D26) -> 0.4 | M26: =IF($E26="Pending","",K26*L26) -> 97290.845 | N26: =IF($E26="Pending","",K26*(1-L26)) -> 145936.27 | O26: =INDEX(Inputs!$C$9:$E$9,1,$D26) -> 24.51 | P26: =INDEX(Inputs!$C$10:$E$10,1,$D26) -> 3 | Q26: =IF($E26="Pending","",(M26*O26+N26*P26)/100) -> 28224.074 | R26: =INDEX(Inputs!$C$12:$E$12,1,$D26) -> 11.4 | S26: =IF($E26="Pending","",I26*R26) -> 3006.3852 | T26: =IF($E26="Pending","",Q26-S26) -> 25217.689 | U26: =INDEX(Inputs!$C$11:$E$11,1,$D26) -> 1100 | V26: =IF($E26="Pending","",I26*U26) -> 290089.8 | W26: =IF($E26="Pending","",IF(T26<=0,"No payback",V26/T26)) -> 11.503425 | X26: =INDEX(Inputs!$C$13:$E$13,1,$D26) -> 0.13096 | Y26: =IF($E26="Pending","",K26*X26/1000) -> 31.853023
A27: 28 | B27: Oxford Telephone Exchange | C27: Central | D27: 2 | E27: =Results!$I$13 -> Sized | F27: =Results!$G$13 -> 3900 | G27: =INDEX(Inputs!$C$5:$E$5,1,$D27) -> 0.4 | H27: =INDEX(Inputs!$C$6:$E$6,1,$D27) -> 230 | I27: =IF($E27="Pending","",F27*G27*H27/1000) -> 358.8 | J27: =INDEX(Inputs!$C$7:$E$7,1,$D27) -> 922.3 | K27: =IF($E27="Pending","",I27*J27) -> 330921.24 | L27: =INDEX(Inputs!$C$8:$E$8,1,$D27) -> 0.6 | M27: =IF($E27="Pending","",K27*L27) -> 198552.74 | N27: =IF($E27="Pending","",K27*(1-L27)) -> 132368.5 | O27: =INDEX(Inputs!$C$9:$E$9,1,$D27) -> 24.51 | P27: =INDEX(Inputs!$C$10:$E$10,1,$D27) -> 4.1 | Q27: =IF($E27="Pending","",(M27*O27+N27*P27)/100) -> 54092.386 | R27: =INDEX(Inputs!$C$12:$E$12,1,$D27) -> 9.5 | S27: =IF($E27="Pending","",I27*R27) -> 3408.6 | T27: =IF($E27="Pending","",Q27-S27) -> 50683.786 | U27: =INDEX(Inputs!$C$11:$E$11,1,$D27) -> 900 | V27: =IF($E27="Pending","",I27*U27) -> 322920 | W27: =IF($E27="Pending","",IF(T27<=0,"No payback",V27/T27)) -> 6.3712683 | X27: =INDEX(Inputs!$C$13:$E$13,1,$D27) -> 0.13096 | Y27: =IF($E27="Pending","",K27*X27/1000) -> 43.337446
A28: 28 | B28: Oxford Telephone Exchange | C28: High | D28: 3 | E28: =Results!$I$13 -> Sized | F28: =Results!$G$13 -> 3900 | G28: =INDEX(Inputs!$C$5:$E$5,1,$D28) -> 0.462 | H28: =INDEX(Inputs!$C$6:$E$6,1,$D28) -> 230 | I28: =IF($E28="Pending","",F28*G28*H28/1000) -> 414.414 | J28: =INDEX(Inputs!$C$7:$E$7,1,$D28) -> 922.3 | K28: =IF($E28="Pending","",I28*J28) -> 382214.03 | L28: =INDEX(Inputs!$C$8:$E$8,1,$D28) -> 0.8 | M28: =IF($E28="Pending","",K28*L28) -> 305771.23 | N28: =IF($E28="Pending","",K28*(1-L28)) -> 76442.806 | O28: =INDEX(Inputs!$C$9:$E$9,1,$D28) -> 24.51 | P28: =INDEX(Inputs!$C$10:$E$10,1,$D28) -> 4.1 | Q28: =IF($E28="Pending","",(M28*O28+N28*P28)/100) -> 78078.682 | R28: =INDEX(Inputs!$C$12:$E$12,1,$D28) -> 7.6 | S28: =IF($E28="Pending","",I28*R28) -> 3149.5464 | T28: =IF($E28="Pending","",Q28-S28) -> 74929.136 | U28: =INDEX(Inputs!$C$11:$E$11,1,$D28) -> 700 | V28: =IF($E28="Pending","",I28*U28) -> 290089.8 | W28: =IF($E28="Pending","",IF(T28<=0,"No payback",V28/T28)) -> 3.871522 | X28: =INDEX(Inputs!$C$13:$E$13,1,$D28) -> 0.13096 | Y28: =IF($E28="Pending","",K28*X28/1000) -> 50.05475
A29: 5 | B29: Oxford Business Park (OxBio Hub) | C29: Low | D29: 1 | E29: =Results!$I$14 -> Sized | F29: =Results!$G$14 -> 3243 | G29: =INDEX(Inputs!$C$5:$E$5,1,$D29) -> 0.294 | H29: =INDEX(Inputs!$C$6:$E$6,1,$D29) -> 230 | I29: =IF($E29="Pending","",F29*G29*H29/1000) -> 219.29166 | J29: =INDEX(Inputs!$C$7:$E$7,1,$D29) -> 922.3 | K29: =IF($E29="Pending","",I29*J29) -> 202252.7 | L29: =INDEX(Inputs!$C$8:$E$8,1,$D29) -> 0.4 | M29: =IF($E29="Pending","",K29*L29) -> 80901.079 | N29: =IF($E29="Pending","",K29*(1-L29)) -> 121351.62 | O29: =INDEX(Inputs!$C$9:$E$9,1,$D29) -> 24.51 | P29: =INDEX(Inputs!$C$10:$E$10,1,$D29) -> 3 | Q29: =IF($E29="Pending","",(M29*O29+N29*P29)/100) -> 23469.403 | R29: =INDEX(Inputs!$C$12:$E$12,1,$D29) -> 11.4 | S29: =IF($E29="Pending","",I29*R29) -> 2499.9249 | T29: =IF($E29="Pending","",Q29-S29) -> 20969.478 | U29: =INDEX(Inputs!$C$11:$E$11,1,$D29) -> 1100 | V29: =IF($E29="Pending","",I29*U29) -> 241220.83 | W29: =IF($E29="Pending","",IF(T29<=0,"No payback",V29/T29)) -> 11.503425 | X29: =INDEX(Inputs!$C$13:$E$13,1,$D29) -> 0.13096 | Y29: =IF($E29="Pending","",K29*X29/1000) -> 26.487013
A30: 5 | B30: Oxford Business Park (OxBio Hub) | C30: Central | D30: 2 | E30: =Results!$I$14 -> Sized | F30: =Results!$G$14 -> 3243 | G30: =INDEX(Inputs!$C$5:$E$5,1,$D30) -> 0.4 | H30: =INDEX(Inputs!$C$6:$E$6,1,$D30) -> 230 | I30: =IF($E30="Pending","",F30*G30*H30/1000) -> 298.356 | J30: =INDEX(Inputs!$C$7:$E$7,1,$D30) -> 922.3 | K30: =IF($E30="Pending","",I30*J30) -> 275173.74 | L30: =INDEX(Inputs!$C$8:$E$8,1,$D30) -> 0.6 | M30: =IF($E30="Pending","",K30*L30) -> 165104.24 | N30: =IF($E30="Pending","",K30*(1-L30)) -> 110069.5 | O30: =INDEX(Inputs!$C$9:$E$9,1,$D30) -> 24.51 | P30: =INDEX(Inputs!$C$10:$E$10,1,$D30) -> 4.1 | Q30: =IF($E30="Pending","",(M30*O30+N30*P30)/100) -> 44979.899 | R30: =INDEX(Inputs!$C$12:$E$12,1,$D30) -> 9.5 | S30: =IF($E30="Pending","",I30*R30) -> 2834.382 | T30: =IF($E30="Pending","",Q30-S30) -> 42145.517 | U30: =INDEX(Inputs!$C$11:$E$11,1,$D30) -> 900 | V30: =IF($E30="Pending","",I30*U30) -> 268520.4 | W30: =IF($E30="Pending","",IF(T30<=0,"No payback",V30/T30)) -> 6.3712683 | X30: =INDEX(Inputs!$C$13:$E$13,1,$D30) -> 0.13096 | Y30: =IF($E30="Pending","",K30*X30/1000) -> 36.036753
A31: 5 | B31: Oxford Business Park (OxBio Hub) | C31: High | D31: 3 | E31: =Results!$I$14 -> Sized | F31: =Results!$G$14 -> 3243 | G31: =INDEX(Inputs!$C$5:$E$5,1,$D31) -> 0.462 | H31: =INDEX(Inputs!$C$6:$E$6,1,$D31) -> 230 | I31: =IF($E31="Pending","",F31*G31*H31/1000) -> 344.60118 | J31: =INDEX(Inputs!$C$7:$E$7,1,$D31) -> 922.3 | K31: =IF($E31="Pending","",I31*J31) -> 317825.67 | L31: =INDEX(Inputs!$C$8:$E$8,1,$D31) -> 0.8 | M31: =IF($E31="Pending","",K31*L31) -> 254260.53 | N31: =IF($E31="Pending","",K31*(1-L31)) -> 63565.134 | O31: =INDEX(Inputs!$C$9:$E$9,1,$D31) -> 24.51 | P31: =INDEX(Inputs!$C$10:$E$10,1,$D31) -> 4.1 | Q31: =IF($E31="Pending","",(M31*O31+N31*P31)/100) -> 64925.428 | R31: =INDEX(Inputs!$C$12:$E$12,1,$D31) -> 7.6 | S31: =IF($E31="Pending","",I31*R31) -> 2618.969 | T31: =IF($E31="Pending","",Q31-S31) -> 62306.459 | U31: =INDEX(Inputs!$C$11:$E$11,1,$D31) -> 700 | V31: =IF($E31="Pending","",I31*U31) -> 241220.83 | W31: =IF($E31="Pending","",IF(T31<=0,"No payback",V31/T31)) -> 3.871522 | X31: =INDEX(Inputs!$C$13:$E$13,1,$D31) -> 0.13096 | Y31: =IF($E31="Pending","",K31*X31/1000) -> 41.62245
A32: 7 | B32: Oxford Business Park (John Wiley & Sons) | C32: Low | D32: 1 | E32: =Results!$I$15 -> Sized | F32: =Results!$G$15 -> 2784 | G32: =INDEX(Inputs!$C$5:$E$5,1,$D32) -> 0.294 | H32: =INDEX(Inputs!$C$6:$E$6,1,$D32) -> 230 | I32: =IF($E32="Pending","",F32*G32*H32/1000) -> 188.25408 | J32: =INDEX(Inputs!$C$7:$E$7,1,$D32) -> 922.3 | K32: =IF($E32="Pending","",I32*J32) -> 173626.74 | L32: =INDEX(Inputs!$C$8:$E$8,1,$D32) -> 0.4 | M32: =IF($E32="Pending","",K32*L32) -> 69450.695 | N32: =IF($E32="Pending","",K32*(1-L32)) -> 104176.04 | O32: =INDEX(Inputs!$C$9:$E$9,1,$D32) -> 24.51 | P32: =INDEX(Inputs!$C$10:$E$10,1,$D32) -> 3 | Q32: =IF($E32="Pending","",(M32*O32+N32*P32)/100) -> 20147.647 | R32: =INDEX(Inputs!$C$12:$E$12,1,$D32) -> 11.4 | S32: =IF($E32="Pending","",I32*R32) -> 2146.0965 | T32: =IF($E32="Pending","",Q32-S32) -> 18001.55 | U32: =INDEX(Inputs!$C$11:$E$11,1,$D32) -> 1100 | V32: =IF($E32="Pending","",I32*U32) -> 207079.49 | W32: =IF($E32="Pending","",IF(T32<=0,"No payback",V32/T32)) -> 11.503425 | X32: =INDEX(Inputs!$C$13:$E$13,1,$D32) -> 0.13096 | Y32: =IF($E32="Pending","",K32*X32/1000) -> 22.738158
A33: 7 | B33: Oxford Business Park (John Wiley & Sons) | C33: Central | D33: 2 | E33: =Results!$I$15 -> Sized | F33: =Results!$G$15 -> 2784 | G33: =INDEX(Inputs!$C$5:$E$5,1,$D33) -> 0.4 | H33: =INDEX(Inputs!$C$6:$E$6,1,$D33) -> 230 | I33: =IF($E33="Pending","",F33*G33*H33/1000) -> 256.128 | J33: =INDEX(Inputs!$C$7:$E$7,1,$D33) -> 922.3 | K33: =IF($E33="Pending","",I33*J33) -> 236226.85 | L33: =INDEX(Inputs!$C$8:$E$8,1,$D33) -> 0.6 | M33: =IF($E33="Pending","",K33*L33) -> 141736.11 | N33: =IF($E33="Pending","",K33*(1-L33)) -> 94490.742 | O33: =INDEX(Inputs!$C$9:$E$9,1,$D33) -> 24.51 | P33: =INDEX(Inputs!$C$10:$E$10,1,$D33) -> 4.1 | Q33: =IF($E33="Pending","",(M33*O33+N33*P33)/100) -> 38613.642 | R33: =INDEX(Inputs!$C$12:$E$12,1,$D33) -> 9.5 | S33: =IF($E33="Pending","",I33*R33) -> 2433.216 | T33: =IF($E33="Pending","",Q33-S33) -> 36180.426 | U33: =INDEX(Inputs!$C$11:$E$11,1,$D33) -> 900 | V33: =IF($E33="Pending","",I33*U33) -> 230515.2 | W33: =IF($E33="Pending","",IF(T33<=0,"No payback",V33/T33)) -> 6.3712683 | X33: =INDEX(Inputs!$C$13:$E$13,1,$D33) -> 0.13096 | Y33: =IF($E33="Pending","",K33*X33/1000) -> 30.936269
A34: 7 | B34: Oxford Business Park (John Wiley & Sons) | C34: High | D34: 3 | E34: =Results!$I$15 -> Sized | F34: =Results!$G$15 -> 2784 | G34: =INDEX(Inputs!$C$5:$E$5,1,$D34) -> 0.462 | H34: =INDEX(Inputs!$C$6:$E$6,1,$D34) -> 230 | I34: =IF($E34="Pending","",F34*G34*H34/1000) -> 295.82784 | J34: =INDEX(Inputs!$C$7:$E$7,1,$D34) -> 922.3 | K34: =IF($E34="Pending","",I34*J34) -> 272842.02 | L34: =INDEX(Inputs!$C$8:$E$8,1,$D34) -> 0.8 | M34: =IF($E34="Pending","",K34*L34) -> 218273.61 | N34: =IF($E34="Pending","",K34*(1-L34)) -> 54568.403 | O34: =INDEX(Inputs!$C$9:$E$9,1,$D34) -> 24.51 | P34: =INDEX(Inputs!$C$10:$E$10,1,$D34) -> 4.1 | Q34: =IF($E34="Pending","",(M34*O34+N34*P34)/100) -> 55736.167 | R34: =INDEX(Inputs!$C$12:$E$12,1,$D34) -> 7.6 | S34: =IF($E34="Pending","",I34*R34) -> 2248.2916 | T34: =IF($E34="Pending","",Q34-S34) -> 53487.876 | U34: =INDEX(Inputs!$C$11:$E$11,1,$D34) -> 700 | V34: =IF($E34="Pending","",I34*U34) -> 207079.49 | W34: =IF($E34="Pending","",IF(T34<=0,"No payback",V34/T34)) -> 3.871522 | X34: =INDEX(Inputs!$C$13:$E$13,1,$D34) -> 0.13096 | Y34: =IF($E34="Pending","",K34*X34/1000) -> 35.731391
A35: 21 | B35: Wickes | C35: Low | D35: 1 | E35: =Results!$I$16 -> Sized | F35: =Results!$G$16 -> 2613 | G35: =INDEX(Inputs!$C$5:$E$5,1,$D35) -> 0.294 | H35: =INDEX(Inputs!$C$6:$E$6,1,$D35) -> 230 | I35: =IF($E35="Pending","",F35*G35*H35/1000) -> 176.69106 | J35: =INDEX(Inputs!$C$7:$E$7,1,$D35) -> 922.3 | K35: =IF($E35="Pending","",I35*J35) -> 162962.16 | L35: =INDEX(Inputs!$C$8:$E$8,1,$D35) -> 0.4 | M35: =IF($E35="Pending","",K35*L35) -> 65184.866 | N35: =IF($E35="Pending","",K35*(1-L35)) -> 97777.299 | O35: =INDEX(Inputs!$C$9:$E$9,1,$D35) -> 24.51 | P35: =INDEX(Inputs!$C$10:$E$10,1,$D35) -> 3 | Q35: =IF($E35="Pending","",(M35*O35+N35*P35)/100) -> 18910.13 | R35: =INDEX(Inputs!$C$12:$E$12,1,$D35) -> 11.4 | S35: =IF($E35="Pending","",I35*R35) -> 2014.2781 | T35: =IF($E35="Pending","",Q35-S35) -> 16895.852 | U35: =INDEX(Inputs!$C$11:$E$11,1,$D35) -> 1100 | V35: =IF($E35="Pending","",I35*U35) -> 194360.17 | W35: =IF($E35="Pending","",IF(T35<=0,"No payback",V35/T35)) -> 11.503425 | X35: =INDEX(Inputs!$C$13:$E$13,1,$D35) -> 0.13096 | Y35: =IF($E35="Pending","",K35*X35/1000) -> 21.341525
A36: 21 | B36: Wickes | C36: Central | D36: 2 | E36: =Results!$I$16 -> Sized | F36: =Results!$G$16 -> 2613 | G36: =INDEX(Inputs!$C$5:$E$5,1,$D36) -> 0.4 | H36: =INDEX(Inputs!$C$6:$E$6,1,$D36) -> 230 | I36: =IF($E36="Pending","",F36*G36*H36/1000) -> 240.396 | J36: =INDEX(Inputs!$C$7:$E$7,1,$D36) -> 922.3 | K36: =IF($E36="Pending","",I36*J36) -> 221717.23 | L36: =INDEX(Inputs!$C$8:$E$8,1,$D36) -> 0.6 | M36: =IF($E36="Pending","",K36*L36) -> 133030.34 | N36: =IF($E36="Pending","",K36*(1-L36)) -> 88686.892 | O36: =INDEX(Inputs!$C$9:$E$9,1,$D36) -> 24.51 | P36: =INDEX(Inputs!$C$10:$E$10,1,$D36) -> 4.1 | Q36: =IF($E36="Pending","",(M36*O36+N36*P36)/100) -> 36241.899 | R36: =INDEX(Inputs!$C$12:$E$12,1,$D36) -> 9.5 | S36: =IF($E36="Pending","",I36*R36) -> 2283.762 | T36: =IF($E36="Pending","",Q36-S36) -> 33958.137 | U36: =INDEX(Inputs!$C$11:$E$11,1,$D36) -> 900 | V36: =IF($E36="Pending","",I36*U36) -> 216356.4 | W36: =IF($E36="Pending","",IF(T36<=0,"No payback",V36/T36)) -> 6.3712683 | X36: =INDEX(Inputs!$C$13:$E$13,1,$D36) -> 0.13096 | Y36: =IF($E36="Pending","",K36*X36/1000) -> 29.036089
A37: 21 | B37: Wickes | C37: High | D37: 3 | E37: =Results!$I$16 -> Sized | F37: =Results!$G$16 -> 2613 | G37: =INDEX(Inputs!$C$5:$E$5,1,$D37) -> 0.462 | H37: =INDEX(Inputs!$C$6:$E$6,1,$D37) -> 230 | I37: =IF($E37="Pending","",F37*G37*H37/1000) -> 277.65738 | J37: =INDEX(Inputs!$C$7:$E$7,1,$D37) -> 922.3 | K37: =IF($E37="Pending","",I37*J37) -> 256083.4 | L37: =INDEX(Inputs!$C$8:$E$8,1,$D37) -> 0.8 | M37: =IF($E37="Pending","",K37*L37) -> 204866.72 | N37: =IF($E37="Pending","",K37*(1-L37)) -> 51216.68 | O37: =INDEX(Inputs!$C$9:$E$9,1,$D37) -> 24.51 | P37: =INDEX(Inputs!$C$10:$E$10,1,$D37) -> 4.1 | Q37: =IF($E37="Pending","",(M37*O37+N37*P37)/100) -> 52312.717 | R37: =INDEX(Inputs!$C$12:$E$12,1,$D37) -> 7.6 | S37: =IF($E37="Pending","",I37*R37) -> 2110.1961 | T37: =IF($E37="Pending","",Q37-S37) -> 50202.521 | U37: =INDEX(Inputs!$C$11:$E$11,1,$D37) -> 700 | V37: =IF($E37="Pending","",I37*U37) -> 194360.17 | W37: =IF($E37="Pending","",IF(T37<=0,"No payback",V37/T37)) -> 3.871522 | X37: =INDEX(Inputs!$C$13:$E$13,1,$D37) -> 0.13096 | Y37: =IF($E37="Pending","",K37*X37/1000) -> 33.536682
A38: 30 | B38: Storage King Oxford - Self Storage Units | C38: Low | D38: 1 | E38: =Results!$I$17 -> Sized | F38: =Results!$G$17 -> 3558 | G38: =INDEX(Inputs!$C$5:$E$5,1,$D38) -> 0.294 | H38: =INDEX(Inputs!$C$6:$E$6,1,$D38) -> 230 | I38: =IF($E38="Pending","",F38*G38*H38/1000) -> 240.59196 | J38: =INDEX(Inputs!$C$7:$E$7,1,$D38) -> 922.3 | K38: =IF($E38="Pending","",I38*J38) -> 221897.96 | L38: =INDEX(Inputs!$C$8:$E$8,1,$D38) -> 0.4 | M38: =IF($E38="Pending","",K38*L38) -> 88759.186 | N38: =IF($E38="Pending","",K38*(1-L38)) -> 133138.78 | O38: =INDEX(Inputs!$C$9:$E$9,1,$D38) -> 24.51 | P38: =INDEX(Inputs!$C$10:$E$10,1,$D38) -> 3 | Q38: =IF($E38="Pending","",(M38*O38+N38*P38)/100) -> 25749.04 | R38: =INDEX(Inputs!$C$12:$E$12,1,$D38) -> 11.4 | S38: =IF($E38="Pending","",I38*R38) -> 2742.7483 | T38: =IF($E38="Pending","",Q38-S38) -> 23006.291 | U38: =INDEX(Inputs!$C$11:$E$11,1,$D38) -> 1100 | V38: =IF($E38="Pending","",I38*U38) -> 264651.16 | W38: =IF($E38="Pending","",IF(T38<=0,"No payback",V38/T38)) -> 11.503425 | X38: =INDEX(Inputs!$C$13:$E$13,1,$D38) -> 0.13096 | Y38: =IF($E38="Pending","",K38*X38/1000) -> 29.059757
A39: 30 | B39: Storage King Oxford - Self Storage Units | C39: Central | D39: 2 | E39: =Results!$I$17 -> Sized | F39: =Results!$G$17 -> 3558 | G39: =INDEX(Inputs!$C$5:$E$5,1,$D39) -> 0.4 | H39: =INDEX(Inputs!$C$6:$E$6,1,$D39) -> 230 | I39: =IF($E39="Pending","",F39*G39*H39/1000) -> 327.336 | J39: =INDEX(Inputs!$C$7:$E$7,1,$D39) -> 922.3 | K39: =IF($E39="Pending","",I39*J39) -> 301901.99 | L39: =INDEX(Inputs!$C$8:$E$8,1,$D39) -> 0.6 | M39: =IF($E39="Pending","",K39*L39) -> 181141.2 | N39: =IF($E39="Pending","",K39*(1-L39)) -> 120760.8 | O39: =INDEX(Inputs!$C$9:$E$9,1,$D39) -> 24.51 | P39: =INDEX(Inputs!$C$10:$E$10,1,$D39) -> 4.1 | Q39: =IF($E39="Pending","",(M39*O39+N39*P39)/100) -> 49348.9 | R39: =INDEX(Inputs!$C$12:$E$12,1,$D39) -> 9.5 | S39: =IF($E39="Pending","",I39*R39) -> 3109.692 | T39: =IF($E39="Pending","",Q39-S39) -> 46239.208 | U39: =INDEX(Inputs!$C$11:$E$11,1,$D39) -> 900 | V39: =IF($E39="Pending","",I39*U39) -> 294602.4 | W39: =IF($E39="Pending","",IF(T39<=0,"No payback",V39/T39)) -> 6.3712683 | X39: =INDEX(Inputs!$C$13:$E$13,1,$D39) -> 0.13096 | Y39: =IF($E39="Pending","",K39*X39/1000) -> 39.537085
A40: 30 | B40: Storage King Oxford - Self Storage Units | C40: High | D40: 3 | E40: =Results!$I$17 -> Sized | F40: =Results!$G$17 -> 3558 | G40: =INDEX(Inputs!$C$5:$E$5,1,$D40) -> 0.462 | H40: =INDEX(Inputs!$C$6:$E$6,1,$D40) -> 230 | I40: =IF($E40="Pending","",F40*G40*H40/1000) -> 378.07308 | J40: =INDEX(Inputs!$C$7:$E$7,1,$D40) -> 922.3 | K40: =IF($E40="Pending","",I40*J40) -> 348696.8 | L40: =INDEX(Inputs!$C$8:$E$8,1,$D40) -> 0.8 | M40: =IF($E40="Pending","",K40*L40) -> 278957.44 | N40: =IF($E40="Pending","",K40*(1-L40)) -> 69739.36 | O40: =INDEX(Inputs!$C$9:$E$9,1,$D40) -> 24.51 | P40: =INDEX(Inputs!$C$10:$E$10,1,$D40) -> 4.1 | Q40: =IF($E40="Pending","",(M40*O40+N40*P40)/100) -> 71231.783 | R40: =INDEX(Inputs!$C$12:$E$12,1,$D40) -> 7.6 | S40: =IF($E40="Pending","",I40*R40) -> 2873.3554 | T40: =IF($E40="Pending","",Q40-S40) -> 68358.427 | U40: =INDEX(Inputs!$C$11:$E$11,1,$D40) -> 700 | V40: =IF($E40="Pending","",I40*U40) -> 264651.16 | W40: =IF($E40="Pending","",IF(T40<=0,"No payback",V40/T40)) -> 3.871522 | X40: =INDEX(Inputs!$C$13:$E$13,1,$D40) -> 0.13096 | Y40: =IF($E40="Pending","",K40*X40/1000) -> 45.665333
A41: 44 | B41: Nuffield Trade and Industrial Park (Royal Mail East Oxford Delivery Office) | C41: Low | D41: 1 | E41: =Results!$I$18 -> Sized | F41: =Results!$G$18 -> 1897 | G41: =INDEX(Inputs!$C$5:$E$5,1,$D41) -> 0.294 | H41: =INDEX(Inputs!$C$6:$E$6,1,$D41) -> 230 | I41: =IF($E41="Pending","",F41*G41*H41/1000) -> 128.27514 | J41: =INDEX(Inputs!$C$7:$E$7,1,$D41) -> 922.3 | K41: =IF($E41="Pending","",I41*J41) -> 118308.16 | L41: =INDEX(Inputs!$C$8:$E$8,1,$D41) -> 0.4 | M41: =IF($E41="Pending","",K41*L41) -> 47323.265 | N41: =IF($E41="Pending","",K41*(1-L41)) -> 70984.897 | O41: =INDEX(Inputs!$C$9:$E$9,1,$D41) -> 24.51 | P41: =INDEX(Inputs!$C$10:$E$10,1,$D41) -> 3 | Q41: =IF($E41="Pending","",(M41*O41+N41*P41)/100) -> 13728.479 | R41: =INDEX(Inputs!$C$12:$E$12,1,$D41) -> 11.4 | S41: =IF($E41="Pending","",I41*R41) -> 1462.3366 | T41: =IF($E41="Pending","",Q41-S41) -> 12266.142 | U41: =INDEX(Inputs!$C$11:$E$11,1,$D41) -> 1100 | V41: =IF($E41="Pending","",I41*U41) -> 141102.65 | W41: =IF($E41="Pending","",IF(T41<=0,"No payback",V41/T41)) -> 11.503425 | X41: =INDEX(Inputs!$C$13:$E$13,1,$D41) -> 0.13096 | Y41: =IF($E41="Pending","",K41*X41/1000) -> 15.493637
A42: 44 | B42: Nuffield Trade and Industrial Park (Royal Mail East Oxford Delivery Office) | C42: Central | D42: 2 | E42: =Results!$I$18 -> Sized | F42: =Results!$G$18 -> 1897 | G42: =INDEX(Inputs!$C$5:$E$5,1,$D42) -> 0.4 | H42: =INDEX(Inputs!$C$6:$E$6,1,$D42) -> 230 | I42: =IF($E42="Pending","",F42*G42*H42/1000) -> 174.524 | J42: =INDEX(Inputs!$C$7:$E$7,1,$D42) -> 922.3 | K42: =IF($E42="Pending","",I42*J42) -> 160963.49 | L42: =INDEX(Inputs!$C$8:$E$8,1,$D42) -> 0.6 | M42: =IF($E42="Pending","",K42*L42) -> 96578.091 | N42: =IF($E42="Pending","",K42*(1-L42)) -> 64385.394 | O42: =INDEX(Inputs!$C$9:$E$9,1,$D42) -> 24.51 | P42: =INDEX(Inputs!$C$10:$E$10,1,$D42) -> 4.1 | Q42: =IF($E42="Pending","",(M42*O42+N42*P42)/100) -> 26311.091 | R42: =INDEX(Inputs!$C$12:$E$12,1,$D42) -> 9.5 | S42: =IF($E42="Pending","",I42*R42) -> 1657.978 | T42: =IF($E42="Pending","",Q42-S42) -> 24653.113 | U42: =INDEX(Inputs!$C$11:$E$11,1,$D42) -> 900 | V42: =IF($E42="Pending","",I42*U42) -> 157071.6 | W42: =IF($E42="Pending","",IF(T42<=0,"No payback",V42/T42)) -> 6.3712683 | X42: =INDEX(Inputs!$C$13:$E$13,1,$D42) -> 0.13096 | Y42: =IF($E42="Pending","",K42*X42/1000) -> 21.079778
A43: 44 | B43: Nuffield Trade and Industrial Park (Royal Mail East Oxford Delivery Office) | C43: High | D43: 3 | E43: =Results!$I$18 -> Sized | F43: =Results!$G$18 -> 1897 | G43: =INDEX(Inputs!$C$5:$E$5,1,$D43) -> 0.462 | H43: =INDEX(Inputs!$C$6:$E$6,1,$D43) -> 230 | I43: =IF($E43="Pending","",F43*G43*H43/1000) -> 201.57522 | J43: =INDEX(Inputs!$C$7:$E$7,1,$D43) -> 922.3 | K43: =IF($E43="Pending","",I43*J43) -> 185912.83 | L43: =INDEX(Inputs!$C$8:$E$8,1,$D43) -> 0.8 | M43: =IF($E43="Pending","",K43*L43) -> 148730.26 | N43: =IF($E43="Pending","",K43*(1-L43)) -> 37182.565 | O43: =INDEX(Inputs!$C$9:$E$9,1,$D43) -> 24.51 | P43: =INDEX(Inputs!$C$10:$E$10,1,$D43) -> 4.1 | Q43: =IF($E43="Pending","",(M43*O43+N43*P43)/100) -> 37978.272 | R43: =INDEX(Inputs!$C$12:$E$12,1,$D43) -> 7.6 | S43: =IF($E43="Pending","",I43*R43) -> 1531.9717 | T43: =IF($E43="Pending","",Q43-S43) -> 36446.3 | U43: =INDEX(Inputs!$C$11:$E$11,1,$D43) -> 700 | V43: =IF($E43="Pending","",I43*U43) -> 141102.65 | W43: =IF($E43="Pending","",IF(T43<=0,"No payback",V43/T43)) -> 3.871522 | X43: =INDEX(Inputs!$C$13:$E$13,1,$D43) -> 0.13096 | Y43: =IF($E43="Pending","",K43*X43/1000) -> 24.347144
A44: 39 | B44: Unicol Engineering | C44: Low | D44: 1 | E44: =Results!$I$19 -> Sized | F44: =Results!$G$19 -> 1652 | G44: =INDEX(Inputs!$C$5:$E$5,1,$D44) -> 0.294 | H44: =INDEX(Inputs!$C$6:$E$6,1,$D44) -> 230 | I44: =IF($E44="Pending","",F44*G44*H44/1000) -> 111.70824 | J44: =INDEX(Inputs!$C$7:$E$7,1,$D44) -> 922.3 | K44: =IF($E44="Pending","",I44*J44) -> 103028.51 | L44: =INDEX(Inputs!$C$8:$E$8,1,$D44) -> 0.4 | M44: =IF($E44="Pending","",K44*L44) -> 41211.404 | N44: =IF($E44="Pending","",K44*(1-L44)) -> 61817.106 | O44: =INDEX(Inputs!$C$9:$E$9,1,$D44) -> 24.51 | P44: =INDEX(Inputs!$C$10:$E$10,1,$D44) -> 3 | Q44: =IF($E44="Pending","",(M44*O44+N44*P44)/100) -> 11955.428 | R44: =INDEX(Inputs!$C$12:$E$12,1,$D44) -> 11.4 | S44: =IF($E44="Pending","",I44*R44) -> 1273.4739 | T44: =IF($E44="Pending","",Q44-S44) -> 10681.954 | U44: =INDEX(Inputs!$C$11:$E$11,1,$D44) -> 1100 | V44: =IF($E44="Pending","",I44*U44) -> 122879.06 | W44: =IF($E44="Pending","",IF(T44<=0,"No payback",V44/T44)) -> 11.503425 | X44: =INDEX(Inputs!$C$13:$E$13,1,$D44) -> 0.13096 | Y44: =IF($E44="Pending","",K44*X44/1000) -> 13.492614
A45: 39 | B45: Unicol Engineering | C45: Central | D45: 2 | E45: =Results!$I$19 -> Sized | F45: =Results!$G$19 -> 1652 | G45: =INDEX(Inputs!$C$5:$E$5,1,$D45) -> 0.4 | H45: =INDEX(Inputs!$C$6:$E$6,1,$D45) -> 230 | I45: =IF($E45="Pending","",F45*G45*H45/1000) -> 151.984 | J45: =INDEX(Inputs!$C$7:$E$7,1,$D45) -> 922.3 | K45: =IF($E45="Pending","",I45*J45) -> 140174.84 | L45: =INDEX(Inputs!$C$8:$E$8,1,$D45) -> 0.6 | M45: =IF($E45="Pending","",K45*L45) -> 84104.906 | N45: =IF($E45="Pending","",K45*(1-L45)) -> 56069.937 | O45: =INDEX(Inputs!$C$9:$E$9,1,$D45) -> 24.51 | P45: =INDEX(Inputs!$C$10:$E$10,1,$D45) -> 4.1 | Q45: =IF($E45="Pending","",(M45*O45+N45*P45)/100) -> 22912.98 | R45: =INDEX(Inputs!$C$12:$E$12,1,$D45) -> 9.5 | S45: =IF($E45="Pending","",I45*R45) -> 1443.848 | T45: =IF($E45="Pending","",Q45-S45) -> 21469.132 | U45: =INDEX(Inputs!$C$11:$E$11,1,$D45) -> 900 | V45: =IF($E45="Pending","",I45*U45) -> 136785.6 | W45: =IF($E45="Pending","",IF(T45<=0,"No payback",V45/T45)) -> 6.3712683 | X45: =INDEX(Inputs!$C$13:$E$13,1,$D45) -> 0.13096 | Y45: =IF($E45="Pending","",K45*X45/1000) -> 18.357297
A46: 39 | B46: Unicol Engineering | C46: High | D46: 3 | E46: =Results!$I$19 -> Sized | F46: =Results!$G$19 -> 1652 | G46: =INDEX(Inputs!$C$5:$E$5,1,$D46) -> 0.462 | H46: =INDEX(Inputs!$C$6:$E$6,1,$D46) -> 230 | I46: =IF($E46="Pending","",F46*G46*H46/1000) -> 175.54152 | J46: =INDEX(Inputs!$C$7:$E$7,1,$D46) -> 922.3 | K46: =IF($E46="Pending","",I46*J46) -> 161901.94 | L46: =INDEX(Inputs!$C$8:$E$8,1,$D46) -> 0.8 | M46: =IF($E46="Pending","",K46*L46) -> 129521.56 | N46: =IF($E46="Pending","",K46*(1-L46)) -> 32380.389 | O46: =INDEX(Inputs!$C$9:$E$9,1,$D46) -> 24.51 | P46: =INDEX(Inputs!$C$10:$E$10,1,$D46) -> 4.1 | Q46: =IF($E46="Pending","",(M46*O46+N46*P46)/100) -> 33073.329 | R46: =INDEX(Inputs!$C$12:$E$12,1,$D46) -> 7.6 | S46: =IF($E46="Pending","",I46*R46) -> 1334.1156 | T46: =IF($E46="Pending","",Q46-S46) -> 31739.214 | U46: =INDEX(Inputs!$C$11:$E$11,1,$D46) -> 700 | V46: =IF($E46="Pending","",I46*U46) -> 122879.06 | W46: =IF($E46="Pending","",IF(T46<=0,"No payback",V46/T46)) -> 3.871522 | X46: =INDEX(Inputs!$C$13:$E$13,1,$D46) -> 0.13096 | Y46: =IF($E46="Pending","",K46*X46/1000) -> 21.202679
A47: 40 | B47: Magdalen Centre (Sherrington Buidling) | C47: Low | D47: 1 | E47: =Results!$I$20 -> Sized | F47: =Results!$G$20 -> 2351 | G47: =INDEX(Inputs!$C$5:$E$5,1,$D47) -> 0.294 | H47: =INDEX(Inputs!$C$6:$E$6,1,$D47) -> 230 | I47: =IF($E47="Pending","",F47*G47*H47/1000) -> 158.97462 | J47: =INDEX(Inputs!$C$7:$E$7,1,$D47) -> 922.3 | K47: =IF($E47="Pending","",I47*J47) -> 146622.29 | L47: =INDEX(Inputs!$C$8:$E$8,1,$D47) -> 0.4 | M47: =IF($E47="Pending","",K47*L47) -> 58648.917 | N47: =IF($E47="Pending","",K47*(1-L47)) -> 87973.375 | O47: =INDEX(Inputs!$C$9:$E$9,1,$D47) -> 24.51 | P47: =INDEX(Inputs!$C$10:$E$10,1,$D47) -> 3 | Q47: =IF($E47="Pending","",(M47*O47+N47*P47)/100) -> 17014.051 | R47: =INDEX(Inputs!$C$12:$E$12,1,$D47) -> 11.4 | S47: =IF($E47="Pending","",I47*R47) -> 1812.3107 | T47: =IF($E47="Pending","",Q47-S47) -> 15201.74 | U47: =INDEX(Inputs!$C$11:$E$11,1,$D47) -> 1100 | V47: =IF($E47="Pending","",I47*U47) -> 174872.08 | W47: =IF($E47="Pending","",IF(T47<=0,"No payback",V47/T47)) -> 11.503425 | X47: =INDEX(Inputs!$C$13:$E$13,1,$D47) -> 0.13096 | Y47: =IF($E47="Pending","",K47*X47/1000) -> 19.201655
A48: 40 | B48: Magdalen Centre (Sherrington Buidling) | C48: Central | D48: 2 | E48: =Results!$I$20 -> Sized | F48: =Results!$G$20 -> 2351 | G48: =INDEX(Inputs!$C$5:$E$5,1,$D48) -> 0.4 | H48: =INDEX(Inputs!$C$6:$E$6,1,$D48) -> 230 | I48: =IF($E48="Pending","",F48*G48*H48/1000) -> 216.292 | J48: =INDEX(Inputs!$C$7:$E$7,1,$D48) -> 922.3 | K48: =IF($E48="Pending","",I48*J48) -> 199486.11 | L48: =INDEX(Inputs!$C$8:$E$8,1,$D48) -> 0.6 | M48: =IF($E48="Pending","",K48*L48) -> 119691.67 | N48: =IF($E48="Pending","",K48*(1-L48)) -> 79794.445 | O48: =INDEX(Inputs!$C$9:$E$9,1,$D48) -> 24.51 | P48: =INDEX(Inputs!$C$10:$E$10,1,$D48) -> 4.1 | Q48: =IF($E48="Pending","",(M48*O48+N48*P48)/100) -> 32608 | R48: =INDEX(Inputs!$C$12:$E$12,1,$D48) -> 9.5 | S48: =IF($E48="Pending","",I48*R48) -> 2054.774 | T48: =IF($E48="Pending","",Q48-S48) -> 30553.226 | U48: =INDEX(Inputs!$C$11:$E$11,1,$D48) -> 900 | V48: =IF($E48="Pending","",I48*U48) -> 194662.8 | W48: =IF($E48="Pending","",IF(T48<=0,"No payback",V48/T48)) -> 6.3712683 | X48: =INDEX(Inputs!$C$13:$E$13,1,$D48) -> 0.13096 | Y48: =IF($E48="Pending","",K48*X48/1000) -> 26.124701
A49: 40 | B49: Magdalen Centre (Sherrington Buidling) | C49: High | D49: 3 | E49: =Results!$I$20 -> Sized | F49: =Results!$G$20 -> 2351 | G49: =INDEX(Inputs!$C$5:$E$5,1,$D49) -> 0.462 | H49: =INDEX(Inputs!$C$6:$E$6,1,$D49) -> 230 | I49: =IF($E49="Pending","",F49*G49*H49/1000) -> 249.81726 | J49: =INDEX(Inputs!$C$7:$E$7,1,$D49) -> 922.3 | K49: =IF($E49="Pending","",I49*J49) -> 230406.46 | L49: =INDEX(Inputs!$C$8:$E$8,1,$D49) -> 0.8 | M49: =IF($E49="Pending","",K49*L49) -> 184325.17 | N49: =IF($E49="Pending","",K49*(1-L49)) -> 46081.292 | O49: =INDEX(Inputs!$C$9:$E$9,1,$D49) -> 24.51 | P49: =INDEX(Inputs!$C$10:$E$10,1,$D49) -> 4.1 | Q49: =IF($E49="Pending","",(M49*O49+N49*P49)/100) -> 47067.431 | R49: =INDEX(Inputs!$C$12:$E$12,1,$D49) -> 7.6 | S49: =IF($E49="Pending","",I49*R49) -> 1898.6112 | T49: =IF($E49="Pending","",Q49-S49) -> 45168.82 | U49: =INDEX(Inputs!$C$11:$E$11,1,$D49) -> 700 | V49: =IF($E49="Pending","",I49*U49) -> 174872.08 | W49: =IF($E49="Pending","",IF(T49<=0,"No payback",V49/T49)) -> 3.871522 | X49: =INDEX(Inputs!$C$13:$E$13,1,$D49) -> 0.13096 | Y49: =IF($E49="Pending","",K49*X49/1000) -> 30.17403
A50: 22 | B50: Sandhills Community Primary School | C50: Low | D50: 1 | E50: =Results!$I$21 -> Sized | F50: =Results!$G$21 -> 2542 | G50: =INDEX(Inputs!$C$5:$E$5,1,$D50) -> 0.294 | H50: =INDEX(Inputs!$C$6:$E$6,1,$D50) -> 230 | I50: =IF($E50="Pending","",F50*G50*H50/1000) -> 171.89004 | J50: =INDEX(Inputs!$C$7:$E$7,1,$D50) -> 922.3 | K50: =IF($E50="Pending","",I50*J50) -> 158534.18 | L50: =INDEX(Inputs!$C$8:$E$8,1,$D50) -> 0.4 | M50: =IF($E50="Pending","",K50*L50) -> 63413.674 | N50: =IF($E50="Pending","",K50*(1-L50)) -> 95120.51 | O50: =INDEX(Inputs!$C$9:$E$9,1,$D50) -> 24.51 | P50: =INDEX(Inputs!$C$10:$E$10,1,$D50) -> 3 | Q50: =IF($E50="Pending","",(M50*O50+N50*P50)/100) -> 18396.307 | R50: =INDEX(Inputs!$C$12:$E$12,1,$D50) -> 11.4 | S50: =IF($E50="Pending","",I50*R50) -> 1959.5465 | T50: =IF($E50="Pending","",Q50-S50) -> 16436.76 | U50: =INDEX(Inputs!$C$11:$E$11,1,$D50) -> 1100 | V50: =IF($E50="Pending","",I50*U50) -> 189079.04 | W50: =IF($E50="Pending","",IF(T50<=0,"No payback",V50/T50)) -> 11.503425 | X50: =INDEX(Inputs!$C$13:$E$13,1,$D50) -> 0.13096 | Y50: =IF($E50="Pending","",K50*X50/1000) -> 20.761637
A51: 22 | B51: Sandhills Community Primary School | C51: Central | D51: 2 | E51: =Results!$I$21 -> Sized | F51: =Results!$G$21 -> 2542 | G51: =INDEX(Inputs!$C$5:$E$5,1,$D51) -> 0.4 | H51: =INDEX(Inputs!$C$6:$E$6,1,$D51) -> 230 | I51: =IF($E51="Pending","",F51*G51*H51/1000) -> 233.864 | J51: =INDEX(Inputs!$C$7:$E$7,1,$D51) -> 922.3 | K51: =IF($E51="Pending","",I51*J51) -> 215692.77 | L51: =INDEX(Inputs!$C$8:$E$8,1,$D51) -> 0.6 | M51: =IF($E51="Pending","",K51*L51) -> 129415.66 | N51: =IF($E51="Pending","",K51*(1-L51)) -> 86277.107 | O51: =INDEX(Inputs!$C$9:$E$9,1,$D51) -> 24.51 | P51: =INDEX(Inputs!$C$10:$E$10,1,$D51) -> 4.1 | Q51: =IF($E51="Pending","",(M51*O51+N51*P51)/100) -> 35257.14 | R51: =INDEX(Inputs!$C$12:$E$12,1,$D51) -> 9.5 | S51: =IF($E51="Pending","",I51*R51) -> 2221.708 | T51: =IF($E51="Pending","",Q51-S51) -> 33035.432 | U51: =INDEX(Inputs!$C$11:$E$11,1,$D51) -> 900 | V51: =IF($E51="Pending","",I51*U51) -> 210477.6 | W51: =IF($E51="Pending","",IF(T51<=0,"No payback",V51/T51)) -> 6.3712683 | X51: =INDEX(Inputs!$C$13:$E$13,1,$D51) -> 0.13096 | Y51: =IF($E51="Pending","",K51*X51/1000) -> 28.247125
A52: 22 | B52: Sandhills Community Primary School | C52: High | D52: 3 | E52: =Results!$I$21 -> Sized | F52: =Results!$G$21 -> 2542 | G52: =INDEX(Inputs!$C$5:$E$5,1,$D52) -> 0.462 | H52: =INDEX(Inputs!$C$6:$E$6,1,$D52) -> 230 | I52: =IF($E52="Pending","",F52*G52*H52/1000) -> 270.11292 | J52: =INDEX(Inputs!$C$7:$E$7,1,$D52) -> 922.3 | K52: =IF($E52="Pending","",I52*J52) -> 249125.15 | L52: =INDEX(Inputs!$C$8:$E$8,1,$D52) -> 0.8 | M52: =IF($E52="Pending","",K52*L52) -> 199300.12 | N52: =IF($E52="Pending","",K52*(1-L52)) -> 49825.029 | O52: =INDEX(Inputs!$C$9:$E$9,1,$D52) -> 24.51 | P52: =INDEX(Inputs!$C$10:$E$10,1,$D52) -> 4.1 | Q52: =IF($E52="Pending","",(M52*O52+N52*P52)/100) -> 50891.285 | R52: =INDEX(Inputs!$C$12:$E$12,1,$D52) -> 7.6 | S52: =IF($E52="Pending","",I52*R52) -> 2052.8582 | T52: =IF($E52="Pending","",Q52-S52) -> 48838.427 | U52: =INDEX(Inputs!$C$11:$E$11,1,$D52) -> 700 | V52: =IF($E52="Pending","",I52*U52) -> 189079.04 | W52: =IF($E52="Pending","",IF(T52<=0,"No payback",V52/T52)) -> 3.871522 | X52: =INDEX(Inputs!$C$13:$E$13,1,$D52) -> 0.13096 | Y52: =IF($E52="Pending","",K52*X52/1000) -> 32.625429
A53: 99 | B53: Oxford Retail Park (TESCO SUPERSTORE) | C53: Low | D53: 1 | E53: =Results!$I$22 -> Sized | F53: =Results!$G$22 -> 6954 | G53: =INDEX(Inputs!$C$5:$E$5,1,$D53) -> 0.294 | H53: =INDEX(Inputs!$C$6:$E$6,1,$D53) -> 230 | I53: =IF($E53="Pending","",F53*G53*H53/1000) -> 470.22948 | J53: =INDEX(Inputs!$C$7:$E$7,1,$D53) -> 922.3 | K53: =IF($E53="Pending","",I53*J53) -> 433692.65 | L53: =INDEX(Inputs!$C$8:$E$8,1,$D53) -> 0.4 | M53: =IF($E53="Pending","",K53*L53) -> 173477.06 | N53: =IF($E53="Pending","",K53*(1-L53)) -> 260215.59 | O53: =INDEX(Inputs!$C$9:$E$9,1,$D53) -> 24.51 | P53: =INDEX(Inputs!$C$10:$E$10,1,$D53) -> 3 | Q53: =IF($E53="Pending","",(M53*O53+N53*P53)/100) -> 50325.695 | R53: =INDEX(Inputs!$C$12:$E$12,1,$D53) -> 11.4 | S53: =IF($E53="Pending","",I53*R53) -> 5360.6161 | T53: =IF($E53="Pending","",Q53-S53) -> 44965.079 | U53: =INDEX(Inputs!$C$11:$E$11,1,$D53) -> 1100 | V53: =IF($E53="Pending","",I53*U53) -> 517252.43 | W53: =IF($E53="Pending","",IF(T53<=0,"No payback",V53/T53)) -> 11.503425 | X53: =INDEX(Inputs!$C$13:$E$13,1,$D53) -> 0.13096 | Y53: =IF($E53="Pending","",K53*X53/1000) -> 56.796389
A54: 99 | B54: Oxford Retail Park (TESCO SUPERSTORE) | C54: Central | D54: 2 | E54: =Results!$I$22 -> Sized | F54: =Results!$G$22 -> 6954 | G54: =INDEX(Inputs!$C$5:$E$5,1,$D54) -> 0.4 | H54: =INDEX(Inputs!$C$6:$E$6,1,$D54) -> 230 | I54: =IF($E54="Pending","",F54*G54*H54/1000) -> 639.768 | J54: =INDEX(Inputs!$C$7:$E$7,1,$D54) -> 922.3 | K54: =IF($E54="Pending","",I54*J54) -> 590058.03 | L54: =INDEX(Inputs!$C$8:$E$8,1,$D54) -> 0.6 | M54: =IF($E54="Pending","",K54*L54) -> 354034.82 | N54: =IF($E54="Pending","",K54*(1-L54)) -> 236023.21 | O54: =INDEX(Inputs!$C$9:$E$9,1,$D54) -> 24.51 | P54: =INDEX(Inputs!$C$10:$E$10,1,$D54) -> 4.1 | Q54: =IF($E54="Pending","",(M54*O54+N54*P54)/100) -> 96450.885 | R54: =INDEX(Inputs!$C$12:$E$12,1,$D54) -> 9.5 | S54: =IF($E54="Pending","",I54*R54) -> 6077.796 | T54: =IF($E54="Pending","",Q54-S54) -> 90373.089 | U54: =INDEX(Inputs!$C$11:$E$11,1,$D54) -> 900 | V54: =IF($E54="Pending","",I54*U54) -> 575791.2 | W54: =IF($E54="Pending","",IF(T54<=0,"No payback",V54/T54)) -> 6.3712683 | X54: =INDEX(Inputs!$C$13:$E$13,1,$D54) -> 0.13096 | Y54: =IF($E54="Pending","",K54*X54/1000) -> 77.273999
A55: 99 | B55: Oxford Retail Park (TESCO SUPERSTORE) | C55: High | D55: 3 | E55: =Results!$I$22 -> Sized | F55: =Results!$G$22 -> 6954 | G55: =INDEX(Inputs!$C$5:$E$5,1,$D55) -> 0.462 | H55: =INDEX(Inputs!$C$6:$E$6,1,$D55) -> 230 | I55: =IF($E55="Pending","",F55*G55*H55/1000) -> 738.93204 | J55: =INDEX(Inputs!$C$7:$E$7,1,$D55) -> 922.3 | K55: =IF($E55="Pending","",I55*J55) -> 681517.02 | L55: =INDEX(Inputs!$C$8:$E$8,1,$D55) -> 0.8 | M55: =IF($E55="Pending","",K55*L55) -> 545213.62 | N55: =IF($E55="Pending","",K55*(1-L55)) -> 136303.4 | O55: =INDEX(Inputs!$C$9:$E$9,1,$D55) -> 24.51 | P55: =INDEX(Inputs!$C$10:$E$10,1,$D55) -> 4.1 | Q55: =IF($E55="Pending","",(M55*O55+N55*P55)/100) -> 139220.3 | R55: =INDEX(Inputs!$C$12:$E$12,1,$D55) -> 7.6 | S55: =IF($E55="Pending","",I55*R55) -> 5615.8835 | T55: =IF($E55="Pending","",Q55-S55) -> 133604.41 | U55: =INDEX(Inputs!$C$11:$E$11,1,$D55) -> 700 | V55: =IF($E55="Pending","",I55*U55) -> 517252.43 | W55: =IF($E55="Pending","",IF(T55<=0,"No payback",V55/T55)) -> 3.871522 | X55: =INDEX(Inputs!$C$13:$E$13,1,$D55) -> 0.13096 | Y55: =IF($E55="Pending","",K55*X55/1000) -> 89.251469
A56: 103 | B56: Oxford University Press | C56: Low | D56: 1 | E56: =Results!$I$23 -> Sized | F56: =Results!$G$23 -> 4584 | G56: =INDEX(Inputs!$C$5:$E$5,1,$D56) -> 0.294 | H56: =INDEX(Inputs!$C$6:$E$6,1,$D56) -> 230 | I56: =IF($E56="Pending","",F56*G56*H56/1000) -> 309.97008 | J56: =INDEX(Inputs!$C$7:$E$7,1,$D56) -> 922.3 | K56: =IF($E56="Pending","",I56*J56) -> 285885.4 | L56: =INDEX(Inputs!$C$8:$E$8,1,$D56) -> 0.4 | M56: =IF($E56="Pending","",K56*L56) -> 114354.16 | N56: =IF($E56="Pending","",K56*(1-L56)) -> 171531.24 | O56: =INDEX(Inputs!$C$9:$E$9,1,$D56) -> 24.51 | P56: =INDEX(Inputs!$C$10:$E$10,1,$D56) -> 3 | Q56: =IF($E56="Pending","",(M56*O56+N56*P56)/100) -> 33174.142 | R56: =INDEX(Inputs!$C$12:$E$12,1,$D56) -> 11.4 | S56: =IF($E56="Pending","",I56*R56) -> 3533.6589 | T56: =IF($E56="Pending","",Q56-S56) -> 29640.483 | U56: =INDEX(Inputs!$C$11:$E$11,1,$D56) -> 1100 | V56: =IF($E56="Pending","",I56*U56) -> 340967.09 | W56: =IF($E56="Pending","",IF(T56<=0,"No payback",V56/T56)) -> 11.503425 | X56: =INDEX(Inputs!$C$13:$E$13,1,$D56) -> 0.13096 | Y56: =IF($E56="Pending","",K56*X56/1000) -> 37.439553
A57: 103 | B57: Oxford University Press | C57: Central | D57: 2 | E57: =Results!$I$23 -> Sized | F57: =Results!$G$23 -> 4584 | G57: =INDEX(Inputs!$C$5:$E$5,1,$D57) -> 0.4 | H57: =INDEX(Inputs!$C$6:$E$6,1,$D57) -> 230 | I57: =IF($E57="Pending","",F57*G57*H57/1000) -> 421.728 | J57: =INDEX(Inputs!$C$7:$E$7,1,$D57) -> 922.3 | K57: =IF($E57="Pending","",I57*J57) -> 388959.73 | L57: =INDEX(Inputs!$C$8:$E$8,1,$D57) -> 0.6 | M57: =IF($E57="Pending","",K57*L57) -> 233375.84 | N57: =IF($E57="Pending","",K57*(1-L57)) -> 155583.89 | O57: =INDEX(Inputs!$C$9:$E$9,1,$D57) -> 24.51 | P57: =INDEX(Inputs!$C$10:$E$10,1,$D57) -> 4.1 | Q57: =IF($E57="Pending","",(M57*O57+N57*P57)/100) -> 63579.358 | R57: =INDEX(Inputs!$C$12:$E$12,1,$D57) -> 9.5 | S57: =IF($E57="Pending","",I57*R57) -> 4006.416 | T57: =IF($E57="Pending","",Q57-S57) -> 59572.942 | U57: =INDEX(Inputs!$C$11:$E$11,1,$D57) -> 900 | V57: =IF($E57="Pending","",I57*U57) -> 379555.2 | W57: =IF($E57="Pending","",IF(T57<=0,"No payback",V57/T57)) -> 6.3712683 | X57: =INDEX(Inputs!$C$13:$E$13,1,$D57) -> 0.13096 | Y57: =IF($E57="Pending","",K57*X57/1000) -> 50.938167
A58: 103 | B58: Oxford University Press | C58: High | D58: 3 | E58: =Results!$I$23 -> Sized | F58: =Results!$G$23 -> 4584 | G58: =INDEX(Inputs!$C$5:$E$5,1,$D58) -> 0.462 | H58: =INDEX(Inputs!$C$6:$E$6,1,$D58) -> 230 | I58: =IF($E58="Pending","",F58*G58*H58/1000) -> 487.09584 | J58: =INDEX(Inputs!$C$7:$E$7,1,$D58) -> 922.3 | K58: =IF($E58="Pending","",I58*J58) -> 449248.49 | L58: =INDEX(Inputs!$C$8:$E$8,1,$D58) -> 0.8 | M58: =IF($E58="Pending","",K58*L58) -> 359398.79 | N58: =IF($E58="Pending","",K58*(1-L58)) -> 89849.699 | O58: =INDEX(Inputs!$C$9:$E$9,1,$D58) -> 24.51 | P58: =INDEX(Inputs!$C$10:$E$10,1,$D58) -> 4.1 | Q58: =IF($E58="Pending","",(M58*O58+N58*P58)/100) -> 91772.482 | R58: =INDEX(Inputs!$C$12:$E$12,1,$D58) -> 7.6 | S58: =IF($E58="Pending","",I58*R58) -> 3701.9284 | T58: =IF($E58="Pending","",Q58-S58) -> 88070.554 | U58: =INDEX(Inputs!$C$11:$E$11,1,$D58) -> 700 | V58: =IF($E58="Pending","",I58*U58) -> 340967.09 | W58: =IF($E58="Pending","",IF(T58<=0,"No payback",V58/T58)) -> 3.871522 | X58: =INDEX(Inputs!$C$13:$E$13,1,$D58) -> 0.13096 | Y58: =IF($E58="Pending","",K58*X58/1000) -> 58.833583
A59: 61 | B59: Leonardo Royal Hotel Oxford | C59: Low | D59: 1 | E59: =Results!$I$24 -> Sized | F59: =Results!$G$24 -> 7218 | G59: =INDEX(Inputs!$C$5:$E$5,1,$D59) -> 0.294 | H59: =INDEX(Inputs!$C$6:$E$6,1,$D59) -> 230 | I59: =IF($E59="Pending","",F59*G59*H59/1000) -> 488.08116 | J59: =INDEX(Inputs!$C$7:$E$7,1,$D59) -> 922.3 | K59: =IF($E59="Pending","",I59*J59) -> 450157.25 | L59: =INDEX(Inputs!$C$8:$E$8,1,$D59) -> 0.4 | M59: =IF($E59="Pending","",K59*L59) -> 180062.9 | N59: =IF($E59="Pending","",K59*(1-L59)) -> 270094.35 | O59: =INDEX(Inputs!$C$9:$E$9,1,$D59) -> 24.51 | P59: =INDEX(Inputs!$C$10:$E$10,1,$D59) -> 3 | Q59: =IF($E59="Pending","",(M59*O59+N59*P59)/100) -> 52236.248 | R59: =INDEX(Inputs!$C$12:$E$12,1,$D59) -> 11.4 | S59: =IF($E59="Pending","",I59*R59) -> 5564.1252 | T59: =IF($E59="Pending","",Q59-S59) -> 46672.123 | U59: =INDEX(Inputs!$C$11:$E$11,1,$D59) -> 1100 | V59: =IF($E59="Pending","",I59*U59) -> 536889.28 | W59: =IF($E59="Pending","",IF(T59<=0,"No payback",V59/T59)) -> 11.503425 | X59: =INDEX(Inputs!$C$13:$E$13,1,$D59) -> 0.13096 | Y59: =IF($E59="Pending","",K59*X59/1000) -> 58.952594
A60: 61 | B60: Leonardo Royal Hotel Oxford | C60: Central | D60: 2 | E60: =Results!$I$24 -> Sized | F60: =Results!$G$24 -> 7218 | G60: =INDEX(Inputs!$C$5:$E$5,1,$D60) -> 0.4 | H60: =INDEX(Inputs!$C$6:$E$6,1,$D60) -> 230 | I60: =IF($E60="Pending","",F60*G60*H60/1000) -> 664.056 | J60: =INDEX(Inputs!$C$7:$E$7,1,$D60) -> 922.3 | K60: =IF($E60="Pending","",I60*J60) -> 612458.85 | L60: =INDEX(Inputs!$C$8:$E$8,1,$D60) -> 0.6 | M60: =IF($E60="Pending","",K60*L60) -> 367475.31 | N60: =IF($E60="Pending","",K60*(1-L60)) -> 244983.54 | O60: =INDEX(Inputs!$C$9:$E$9,1,$D60) -> 24.51 | P60: =INDEX(Inputs!$C$10:$E$10,1,$D60) -> 4.1 | Q60: =IF($E60="Pending","",(M60*O60+N60*P60)/100) -> 100112.52 | R60: =INDEX(Inputs!$C$12:$E$12,1,$D60) -> 9.5 | S60: =IF($E60="Pending","",I60*R60) -> 6308.532 | T60: =IF($E60="Pending","",Q60-S60) -> 93803.991 | U60: =INDEX(Inputs!$C$11:$E$11,1,$D60) -> 900 | V60: =IF($E60="Pending","",I60*U60) -> 597650.4 | W60: =IF($E60="Pending","",IF(T60<=0,"No payback",V60/T60)) -> 6.3712683 | X60: =INDEX(Inputs!$C$13:$E$13,1,$D60) -> 0.13096 | Y60: =IF($E60="Pending","",K60*X60/1000) -> 80.207611
A61: 61 | B61: Leonardo Royal Hotel Oxford | C61: High | D61: 3 | E61: =Results!$I$24 -> Sized | F61: =Results!$G$24 -> 7218 | G61: =INDEX(Inputs!$C$5:$E$5,1,$D61) -> 0.462 | H61: =INDEX(Inputs!$C$6:$E$6,1,$D61) -> 230 | I61: =IF($E61="Pending","",F61*G61*H61/1000) -> 766.98468 | J61: =INDEX(Inputs!$C$7:$E$7,1,$D61) -> 922.3 | K61: =IF($E61="Pending","",I61*J61) -> 707389.97 | L61: =INDEX(Inputs!$C$8:$E$8,1,$D61) -> 0.8 | M61: =IF($E61="Pending","",K61*L61) -> 565911.98 | N61: =IF($E61="Pending","",K61*(1-L61)) -> 141477.99 | O61: =INDEX(Inputs!$C$9:$E$9,1,$D61) -> 24.51 | P61: =INDEX(Inputs!$C$10:$E$10,1,$D61) -> 4.1 | Q61: =IF($E61="Pending","",(M61*O61+N61*P61)/100) -> 144505.62 | R61: =INDEX(Inputs!$C$12:$E$12,1,$D61) -> 7.6 | S61: =IF($E61="Pending","",I61*R61) -> 5829.0836 | T61: =IF($E61="Pending","",Q61-S61) -> 138676.54 | U61: =INDEX(Inputs!$C$11:$E$11,1,$D61) -> 700 | V61: =IF($E61="Pending","",I61*U61) -> 536889.28 | W61: =IF($E61="Pending","",IF(T61<=0,"No payback",V61/T61)) -> 3.871522 | X61: =INDEX(Inputs!$C$13:$E$13,1,$D61) -> 0.13096 | Y61: =IF($E61="Pending","",K61*X61/1000) -> 92.639791
A62: 52 | B62: The Manor Hospital | C62: Low | D62: 1 | E62: =Results!$I$25 -> Sized | F62: =Results!$G$25 -> 4354 | G62: =INDEX(Inputs!$C$5:$E$5,1,$D62) -> 0.294 | H62: =INDEX(Inputs!$C$6:$E$6,1,$D62) -> 230 | I62: =IF($E62="Pending","",F62*G62*H62/1000) -> 294.41748 | J62: =INDEX(Inputs!$C$7:$E$7,1,$D62) -> 922.3 | K62: =IF($E62="Pending","",I62*J62) -> 271541.24 | L62: =INDEX(Inputs!$C$8:$E$8,1,$D62) -> 0.4 | M62: =IF($E62="Pending","",K62*L62) -> 108616.5 | N62: =IF($E62="Pending","",K62*(1-L62)) -> 162924.75 | O62: =INDEX(Inputs!$C$9:$E$9,1,$D62) -> 24.51 | P62: =INDEX(Inputs!$C$10:$E$10,1,$D62) -> 3 | Q62: =IF($E62="Pending","",(M62*O62+N62*P62)/100) -> 31509.646 | R62: =INDEX(Inputs!$C$12:$E$12,1,$D62) -> 11.4 | S62: =IF($E62="Pending","",I62*R62) -> 3356.3593 | T62: =IF($E62="Pending","",Q62-S62) -> 28153.286 | U62: =INDEX(Inputs!$C$11:$E$11,1,$D62) -> 1100 | V62: =IF($E62="Pending","",I62*U62) -> 323859.23 | W62: =IF($E62="Pending","",IF(T62<=0,"No payback",V62/T62)) -> 11.503425 | X62: =INDEX(Inputs!$C$13:$E$13,1,$D62) -> 0.13096 | Y62: =IF($E62="Pending","",K62*X62/1000) -> 35.561041
A63: 52 | B63: The Manor Hospital | C63: Central | D63: 2 | E63: =Results!$I$25 -> Sized | F63: =Results!$G$25 -> 4354 | G63: =INDEX(Inputs!$C$5:$E$5,1,$D63) -> 0.4 | H63: =INDEX(Inputs!$C$6:$E$6,1,$D63) -> 230 | I63: =IF($E63="Pending","",F63*G63*H63/1000) -> 400.568 | J63: =INDEX(Inputs!$C$7:$E$7,1,$D63) -> 922.3 | K63: =IF($E63="Pending","",I63*J63) -> 369443.87 | L63: =INDEX(Inputs!$C$8:$E$8,1,$D63) -> 0.6 | M63: =IF($E63="Pending","",K63*L63) -> 221666.32 | N63: =IF($E63="Pending","",K63*(1-L63)) -> 147777.55 | O63: =INDEX(Inputs!$C$9:$E$9,1,$D63) -> 24.51 | P63: =INDEX(Inputs!$C$10:$E$10,1,$D63) -> 4.1 | Q63: =IF($E63="Pending","",(M63*O63+N63*P63)/100) -> 60389.294 | R63: =INDEX(Inputs!$C$12:$E$12,1,$D63) -> 9.5 | S63: =IF($E63="Pending","",I63*R63) -> 3805.396 | T63: =IF($E63="Pending","",Q63-S63) -> 56583.898 | U63: =INDEX(Inputs!$C$11:$E$11,1,$D63) -> 900 | V63: =IF($E63="Pending","",I63*U63) -> 360511.2 | W63: =IF($E63="Pending","",IF(T63<=0,"No payback",V63/T63)) -> 6.3712683 | X63: =INDEX(Inputs!$C$13:$E$13,1,$D63) -> 0.13096 | Y63: =IF($E63="Pending","",K63*X63/1000) -> 48.382369
A64: 52 | B64: The Manor Hospital | C64: High | D64: 3 | E64: =Results!$I$25 -> Sized | F64: =Results!$G$25 -> 4354 | G64: =INDEX(Inputs!$C$5:$E$5,1,$D64) -> 0.462 | H64: =INDEX(Inputs!$C$6:$E$6,1,$D64) -> 230 | I64: =IF($E64="Pending","",F64*G64*H64/1000) -> 462.65604 | J64: =INDEX(Inputs!$C$7:$E$7,1,$D64) -> 922.3 | K64: =IF($E64="Pending","",I64*J64) -> 426707.67 | L64: =INDEX(Inputs!$C$8:$E$8,1,$D64) -> 0.8 | M64: =IF($E64="Pending","",K64*L64) -> 341366.13 | N64: =IF($E64="Pending","",K64*(1-L64)) -> 85341.533 | O64: =INDEX(Inputs!$C$9:$E$9,1,$D64) -> 24.51 | P64: =INDEX(Inputs!$C$10:$E$10,1,$D64) -> 4.1 | Q64: =IF($E64="Pending","",(M64*O64+N64*P64)/100) -> 87167.842 | R64: =INDEX(Inputs!$C$12:$E$12,1,$D64) -> 7.6 | S64: =IF($E64="Pending","",I64*R64) -> 3516.1859 | T64: =IF($E64="Pending","",Q64-S64) -> 83651.656 | U64: =INDEX(Inputs!$C$11:$E$11,1,$D64) -> 700 | V64: =IF($E64="Pending","",I64*U64) -> 323859.23 | W64: =IF($E64="Pending","",IF(T64<=0,"No payback",V64/T64)) -> 3.871522 | X64: =INDEX(Inputs!$C$13:$E$13,1,$D64) -> 0.13096 | Y64: =IF($E64="Pending","",K64*X64/1000) -> 55.881636
